{
  "parent": "minecraft:recipes/root",
  "rewards": {
    "recipes": [
      "minecraft:originium_dust_from_originite"
    ]
  },
  "criteria": {
    "has_originite": {
      "trigger": "minecraft:inventory_changed",
      "conditions": {
        "items": [
          {
            "items": [
              "projectazure:originite"
            ]
          }
        ]
      }
    },
    "has_the_recipe": {
      "trigger": "minecraft:recipe_unlocked",
      "conditions": {
        "recipe": "minecraft:originium_dust_from_originite"
      }
    }
  },
  "requirements": [
    [
      "has_originite",
      "has_the_recipe"
    ]
  ]
}