{
	"format_version": "1.12.0",
	"minecraft:geometry": [
		{
			"description": {
				"identifier": "geometry.unknown",
				"texture_width": 256,
				"texture_height": 256,
				"visible_bounds_width": 4,
				"visible_bounds_height": 6.5,
				"visible_bounds_offset": [0, 2.75, 0]
			},
			"bones": [
				{
					"name": "Body",
					"pivot": [0, 31.65, 0],
					"cubes": [
						{
							"origin": [-6.75, 30.75, -4],
							"size": [13.5, 8.5, 8],
							"uv": {
								"north": {"uv": [77, 90], "uv_size": [13.5, 8.5]},
								"east": {"uv": [45, 24], "uv_size": [8, 8.5]},
								"south": {"uv": [92, 90], "uv_size": [13.5, 8.5]},
								"west": {"uv": [49, 0], "uv_size": [8, 8.5]},
								"up": {"uv": [94, 51], "uv_size": [13.5, 8]},
								"down": {"uv": [94, 68], "uv_size": [13.5, -8]}
							}
						},
						{
							"origin": [-7, 30.75, -4.25],
							"size": [14, 1, 8.5],
							"uv": {
								"north": {"uv": [139, 131], "uv_size": [14, 1]},
								"east": {"uv": [99, 31], "uv_size": [8.5, 1]},
								"south": {"uv": [145, 29], "uv_size": [14, 1]},
								"west": {"uv": [154, 6], "uv_size": [8.5, 1]},
								"up": {"uv": [32, 87], "uv_size": [14, 8.5]},
								"down": {"uv": [47, 95.5], "uv_size": [14, -8.5]}
							}
						}
					]
				},
				{
					"name": "Chest",
					"parent": "Body",
					"pivot": [0, 39.28702, 3.9046],
					"cubes": [
						{
							"origin": [-7.25, 39.25, -4.25],
							"size": [14.5, 9.5, 8.5],
							"uv": {
								"north": {"uv": [78, 48], "uv_size": [14.5, 9.5]},
								"east": {"uv": [54, 37], "uv_size": [8.5, 9.5]},
								"south": {"uv": [78, 59], "uv_size": [14.5, 9.5]},
								"west": {"uv": [32, 109], "uv_size": [8.5, 9.5]},
								"up": {"uv": [84, 0], "uv_size": [14.5, 8.5]},
								"down": {"uv": [16, 95.5], "uv_size": [14.5, -8.5]}
							}
						}
					]
				},
				{
					"name": "cosmetic_chest",
					"parent": "Chest",
					"pivot": [0, 39.75, 3.75]
				},
				{
					"name": "jacket",
					"parent": "cosmetic_chest",
					"pivot": [0, 39.75, 3.75],
					"cubes": [
						{
							"origin": [-7.5, 38.75, -4.25],
							"size": [15, 10.25, 9],
							"uv": {
								"north": {"uv": [16, 0], "uv_size": [15, 10.5]},
								"east": {"uv": [99, 19], "uv_size": [9, 10.5]},
								"south": {"uv": [16, 12], "uv_size": [15, 10.5]},
								"west": {"uv": [68, 100], "uv_size": [9, 10.5]},
								"up": {"uv": [79.5, 13], "uv_size": [15.5, 9]},
								"down": {"uv": [81, 79], "uv_size": [15, -9]}
							}
						},
						{
							"origin": [-2, 42, 5.75],
							"size": [4, 7, 1],
							"uv": {
								"north": {"uv": [21, 139], "uv_size": [4, 7]},
								"east": {"uv": [26, 38], "uv_size": [1, 7]},
								"south": {"uv": [26, 139], "uv_size": [4, 7]},
								"west": {"uv": [24, 77], "uv_size": [1, 7]},
								"up": {"uv": [162, 4], "uv_size": [4, 1]},
								"down": {"uv": [19, 164], "uv_size": [4, -1]}
							}
						},
						{
							"origin": [-3, 42, 4.75],
							"size": [6, 7, 1],
							"uv": {
								"north": {"uv": [0, 132], "uv_size": [6, 7]},
								"east": {"uv": [50, 109], "uv_size": [1, 7]},
								"south": {"uv": [35, 133], "uv_size": [6, 7]},
								"west": {"uv": [48, 122], "uv_size": [1, 7]},
								"up": {"uv": [159, 12], "uv_size": [6, 1]},
								"down": {"uv": [159, 125], "uv_size": [6, -1]}
							}
						},
						{
							"origin": [-2, 43, 6.75],
							"size": [4, 6, 1],
							"uv": {
								"north": {"uv": [141, 142], "uv_size": [4, 6]},
								"east": {"uv": [116, 124], "uv_size": [1, 6]},
								"south": {"uv": [143, 37], "uv_size": [4, 6]},
								"west": {"uv": [104, 133], "uv_size": [1, 6]},
								"up": {"uv": [163, 25], "uv_size": [4, 1]},
								"down": {"uv": [163, 28], "uv_size": [4, -1]}
							}
						},
						{
							"origin": [-7, 46, 5.75],
							"size": [5, 3, 1],
							"uv": {
								"north": {"uv": [102, 147], "uv_size": [5, 3]},
								"east": {"uv": [46, 136], "uv_size": [1, 3]},
								"south": {"uv": [148, 0], "uv_size": [5, 3]},
								"west": {"uv": [88, 157], "uv_size": [1, 3]},
								"up": {"uv": [160, 55], "uv_size": [5, 1]},
								"down": {"uv": [160, 86], "uv_size": [5, -1]}
							}
						},
						{
							"origin": [-7.25, 46, 4.75],
							"size": [5.25, 3, 1],
							"uv": {
								"north": {"uv": [14, 144], "uv_size": [5.5, 3]},
								"east": {"uv": [71, 166], "uv_size": [1, 3]},
								"south": {"uv": [76, 144], "uv_size": [5.5, 3]},
								"west": {"uv": [73, 166], "uv_size": [1, 3]},
								"up": {"uv": [159, 126], "uv_size": [5.5, 1]},
								"down": {"uv": [159, 132], "uv_size": [5.5, -1]}
							}
						},
						{
							"origin": [2, 46, 4.75],
							"size": [5.25, 3, 1],
							"uv": {
								"north": {"uv": [83, 144], "uv_size": [5.5, 3]},
								"east": {"uv": [75, 166], "uv_size": [1, 3]},
								"south": {"uv": [145, 15], "uv_size": [5.5, 3]},
								"west": {"uv": [77, 166], "uv_size": [1, 3]},
								"up": {"uv": [159, 133], "uv_size": [5.5, 1]},
								"down": {"uv": [159, 136], "uv_size": [5.5, -1]}
							}
						},
						{
							"origin": [-6.25, 46.5, 6.75],
							"size": [3, 3, 1.25],
							"uv": {
								"north": {"uv": [154, 31], "uv_size": [3, 3]},
								"east": {"uv": [91, 161], "uv_size": [1.5, 3]},
								"south": {"uv": [154, 43], "uv_size": [3, 3]},
								"west": {"uv": [94, 161], "uv_size": [1.5, 3]},
								"up": {"uv": [161, 94], "uv_size": [3, 1.5]},
								"down": {"uv": [97, 162.5], "uv_size": [3, -1.5]}
							}
						},
						{
							"origin": [-4.25, 46.5, 7.75],
							"size": [8.5, 3, 1.25],
							"uv": {
								"north": {"uv": [83, 33], "uv_size": [8.5, 3]},
								"east": {"uv": [161, 111], "uv_size": [1.5, 3]},
								"south": {"uv": [139, 61], "uv_size": [8.5, 3]},
								"west": {"uv": [114, 161], "uv_size": [1.5, 3]},
								"up": {"uv": [148, 37], "uv_size": [8.5, 1.5]},
								"down": {"uv": [148, 41.5], "uv_size": [8.5, -1.5]}
							}
						},
						{
							"origin": [-7.25, 46.5, 5.75],
							"size": [3, 3, 1.25],
							"uv": {
								"north": {"uv": [45, 154], "uv_size": [3, 3]},
								"east": {"uv": [161, 97], "uv_size": [1.5, 3]},
								"south": {"uv": [49, 154], "uv_size": [3, 3]},
								"west": {"uv": [161, 101], "uv_size": [1.5, 3]},
								"up": {"uv": [161, 105], "uv_size": [3, 1.5]},
								"down": {"uv": [161, 109.5], "uv_size": [3, -1.5]}
							}
						},
						{
							"origin": [3.25, 46.5, 6.75],
							"size": [3, 3, 1.25],
							"uv": {
								"north": {"uv": [65, 154], "uv_size": [3, 3]},
								"east": {"uv": [126, 161], "uv_size": [1.5, 3]},
								"south": {"uv": [154, 69], "uv_size": [3, 3]},
								"west": {"uv": [162, 0], "uv_size": [1.5, 3]},
								"up": {"uv": [50, 162], "uv_size": [3, 1.5]},
								"down": {"uv": [162, 61.5], "uv_size": [3, -1.5]}
							}
						},
						{
							"origin": [4.25, 46.5, 5.75],
							"size": [3, 3, 1.25],
							"uv": {
								"north": {"uv": [53, 154], "uv_size": [3, 3]},
								"east": {"uv": [117, 161], "uv_size": [1.5, 3]},
								"south": {"uv": [57, 154], "uv_size": [3, 3]},
								"west": {"uv": [123, 161], "uv_size": [1.5, 3]},
								"up": {"uv": [161, 158], "uv_size": [3, 1.5]},
								"down": {"uv": [161, 162.5], "uv_size": [3, -1.5]}
							}
						},
						{
							"origin": [2, 46, 6.75],
							"size": [4, 3, 1],
							"uv": {
								"north": {"uv": [65, 150], "uv_size": [4, 3]},
								"east": {"uv": [165, 157], "uv_size": [1, 3]},
								"south": {"uv": [151, 8], "uv_size": [4, 3]},
								"west": {"uv": [158, 165], "uv_size": [1, 3]},
								"up": {"uv": [163, 31], "uv_size": [4, 1]},
								"down": {"uv": [163, 34], "uv_size": [4, -1]}
							}
						},
						{
							"origin": [-6, 46, 6.75],
							"size": [4, 3, 1],
							"uv": {
								"north": {"uv": [102, 151], "uv_size": [4, 3]},
								"east": {"uv": [0, 166], "uv_size": [1, 3]},
								"south": {"uv": [129, 151], "uv_size": [4, 3]},
								"west": {"uv": [166, 12], "uv_size": [1, 3]},
								"up": {"uv": [163, 35], "uv_size": [4, 1]},
								"down": {"uv": [163, 48], "uv_size": [4, -1]}
							}
						},
						{
							"origin": [-4, 45, 7.75],
							"size": [8, 4, 1],
							"uv": {
								"north": {"uv": [97, 85], "uv_size": [8, 4]},
								"east": {"uv": [11, 163], "uv_size": [1, 4]},
								"south": {"uv": [118, 40], "uv_size": [8, 4]},
								"west": {"uv": [29, 163], "uv_size": [1, 4]},
								"up": {"uv": [154, 137], "uv_size": [8, 1]},
								"down": {"uv": [155, 59], "uv_size": [8, -1]}
							}
						},
						{
							"origin": [-2, 44, 7.75],
							"size": [4, 1, 1],
							"uv": {
								"north": {"uv": [163, 74], "uv_size": [4, 1]},
								"east": {"uv": [172, 28], "uv_size": [1, 1]},
								"south": {"uv": [163, 76], "uv_size": [4, 1]},
								"west": {"uv": [36, 172], "uv_size": [1, 1]},
								"up": {"uv": [163, 78], "uv_size": [4, 1]},
								"down": {"uv": [163, 81], "uv_size": [4, -1]}
							}
						},
						{
							"origin": [-4, 44, 6.75],
							"size": [2, 2, 1],
							"uv": {
								"north": {"uv": [38, 163], "uv_size": [2, 2]},
								"east": {"uv": [158, 169], "uv_size": [1, 2]},
								"south": {"uv": [41, 163], "uv_size": [2, 2]},
								"west": {"uv": [169, 166], "uv_size": [1, 2]},
								"up": {"uv": [169, 169], "uv_size": [2, 1]},
								"down": {"uv": [0, 171], "uv_size": [2, -1]}
							}
						},
						{
							"origin": [2, 44, 6.75],
							"size": [2, 2, 1],
							"uv": {
								"north": {"uv": [44, 163], "uv_size": [2, 2]},
								"east": {"uv": [170, 0], "uv_size": [1, 2]},
								"south": {"uv": [47, 163], "uv_size": [2, 2]},
								"west": {"uv": [3, 170], "uv_size": [1, 2]},
								"up": {"uv": [5, 170], "uv_size": [2, 1]},
								"down": {"uv": [8, 171], "uv_size": [2, -1]}
							}
						},
						{
							"origin": [4, 45, 6.75],
							"size": [1, 1, 1],
							"uv": {
								"north": {"uv": [171, 166], "uv_size": [1, 1]},
								"east": {"uv": [168, 171], "uv_size": [1, 1]},
								"south": {"uv": [170, 171], "uv_size": [1, 1]},
								"west": {"uv": [0, 172], "uv_size": [1, 1]},
								"up": {"uv": [172, 0], "uv_size": [1, 1]},
								"down": {"uv": [5, 173], "uv_size": [1, -1]}
							}
						},
						{
							"origin": [-5, 45, 6.75],
							"size": [1, 1, 1],
							"uv": {
								"north": {"uv": [172, 5], "uv_size": [1, 1]},
								"east": {"uv": [7, 172], "uv_size": [1, 1]},
								"south": {"uv": [9, 172], "uv_size": [1, 1]},
								"west": {"uv": [13, 172], "uv_size": [1, 1]},
								"up": {"uv": [17, 172], "uv_size": [1, 1]},
								"down": {"uv": [19, 173], "uv_size": [1, -1]}
							}
						},
						{
							"origin": [2, 46, 5.75],
							"size": [5, 3, 1],
							"uv": {
								"north": {"uv": [148, 4], "uv_size": [5, 3]},
								"east": {"uv": [59, 165], "uv_size": [1, 3]},
								"south": {"uv": [14, 148], "uv_size": [5, 3]},
								"west": {"uv": [95, 165], "uv_size": [1, 3]},
								"up": {"uv": [160, 119], "uv_size": [5, 1]},
								"down": {"uv": [160, 122], "uv_size": [5, -1]}
							}
						},
						{
							"origin": [2, 45, 5.75],
							"size": [4, 1, 1],
							"uv": {
								"north": {"uv": [163, 19], "uv_size": [4, 1]},
								"east": {"uv": [128, 171], "uv_size": [1, 1]},
								"south": {"uv": [163, 21], "uv_size": [4, 1]},
								"west": {"uv": [130, 171], "uv_size": [1, 1]},
								"up": {"uv": [163, 23], "uv_size": [4, 1]},
								"down": {"uv": [24, 164], "uv_size": [4, -1]}
							}
						},
						{
							"origin": [2, 43, 5.75],
							"size": [2, 1, 1],
							"uv": {
								"north": {"uv": [169, 153], "uv_size": [2, 1]},
								"east": {"uv": [171, 136], "uv_size": [1, 1]},
								"south": {"uv": [169, 155], "uv_size": [2, 1]},
								"west": {"uv": [171, 138], "uv_size": [1, 1]},
								"up": {"uv": [169, 160], "uv_size": [2, 1]},
								"down": {"uv": [166, 170], "uv_size": [2, -1]}
							}
						},
						{
							"origin": [-7, 45, 4.75],
							"size": [5, 1, 1],
							"uv": {
								"north": {"uv": [160, 141], "uv_size": [5, 1]},
								"east": {"uv": [171, 146], "uv_size": [1, 1]},
								"south": {"uv": [160, 143], "uv_size": [5, 1]},
								"west": {"uv": [171, 148], "uv_size": [1, 1]},
								"up": {"uv": [160, 145], "uv_size": [5, 1]},
								"down": {"uv": [19, 162], "uv_size": [5, -1]}
							}
						},
						{
							"origin": [-6, 44, 4.75],
							"size": [4, 1, 1],
							"uv": {
								"north": {"uv": [163, 49], "uv_size": [4, 1]},
								"east": {"uv": [171, 150], "uv_size": [1, 1]},
								"south": {"uv": [163, 51], "uv_size": [4, 1]},
								"west": {"uv": [160, 171], "uv_size": [1, 1]},
								"up": {"uv": [163, 53], "uv_size": [4, 1]},
								"down": {"uv": [163, 73], "uv_size": [4, -1]}
							}
						},
						{
							"origin": [2, 44, 5.75],
							"size": [3, 1, 1],
							"uv": {
								"north": {"uv": [165, 161], "uv_size": [3, 1]},
								"east": {"uv": [162, 171], "uv_size": [1, 1]},
								"south": {"uv": [166, 16], "uv_size": [3, 1]},
								"west": {"uv": [166, 171], "uv_size": [1, 1]},
								"up": {"uv": [166, 29], "uv_size": [3, 1]},
								"down": {"uv": [37, 167], "uv_size": [3, -1]}
							}
						},
						{
							"origin": [-5, 43, 4.75],
							"size": [3, 1, 1],
							"uv": {
								"north": {"uv": [165, 151], "uv_size": [3, 1]},
								"east": {"uv": [171, 140], "uv_size": [1, 1]},
								"south": {"uv": [165, 153], "uv_size": [3, 1]},
								"west": {"uv": [141, 171], "uv_size": [1, 1]},
								"up": {"uv": [154, 165], "uv_size": [3, 1]},
								"down": {"uv": [165, 156], "uv_size": [3, -1]}
							}
						},
						{
							"origin": [2, 43, 4.75],
							"size": [3, 1, 1],
							"uv": {
								"north": {"uv": [166, 120], "uv_size": [3, 1]},
								"east": {"uv": [74, 172], "uv_size": [1, 1]},
								"south": {"uv": [166, 122], "uv_size": [3, 1]},
								"west": {"uv": [76, 172], "uv_size": [1, 1]},
								"up": {"uv": [166, 124], "uv_size": [3, 1]},
								"down": {"uv": [166, 127], "uv_size": [3, -1]}
							}
						},
						{
							"origin": [2, 44, 4.75],
							"size": [4, 1, 1],
							"uv": {
								"north": {"uv": [164, 97], "uv_size": [4, 1]},
								"east": {"uv": [70, 172], "uv_size": [1, 1]},
								"south": {"uv": [164, 99], "uv_size": [4, 1]},
								"west": {"uv": [72, 172], "uv_size": [1, 1]},
								"up": {"uv": [164, 101], "uv_size": [4, 1]},
								"down": {"uv": [102, 165], "uv_size": [4, -1]}
							}
						},
						{
							"origin": [2, 45, 4.75],
							"size": [5, 1, 1],
							"uv": {
								"north": {"uv": [25, 161], "uv_size": [5, 1]},
								"east": {"uv": [59, 172], "uv_size": [1, 1]},
								"south": {"uv": [161, 37], "uv_size": [5, 1]},
								"west": {"uv": [65, 172], "uv_size": [1, 1]},
								"up": {"uv": [38, 161], "uv_size": [5, 1]},
								"down": {"uv": [161, 40], "uv_size": [5, -1]}
							}
						},
						{
							"origin": [-6, 45, 5.75],
							"size": [4, 1, 1],
							"uv": {
								"north": {"uv": [164, 57], "uv_size": [4, 1]},
								"east": {"uv": [54, 172], "uv_size": [1, 1]},
								"south": {"uv": [72, 164], "uv_size": [4, 1]},
								"west": {"uv": [172, 57], "uv_size": [1, 1]},
								"up": {"uv": [77, 164], "uv_size": [4, 1]},
								"down": {"uv": [97, 165], "uv_size": [4, -1]}
							}
						},
						{
							"origin": [-5, 44, 5.75],
							"size": [3, 1, 1],
							"uv": {
								"north": {"uv": [166, 84], "uv_size": [3, 1]},
								"east": {"uv": [50, 172], "uv_size": [1, 1]},
								"south": {"uv": [97, 166], "uv_size": [3, 1]},
								"west": {"uv": [52, 172], "uv_size": [1, 1]},
								"up": {"uv": [101, 166], "uv_size": [3, 1]},
								"down": {"uv": [166, 119], "uv_size": [3, -1]}
							}
						},
						{
							"origin": [-4, 43, 5.75],
							"size": [2, 1, 1],
							"uv": {
								"north": {"uv": [170, 16], "uv_size": [2, 1]},
								"east": {"uv": [46, 172], "uv_size": [1, 1]},
								"south": {"uv": [36, 170], "uv_size": [2, 1]},
								"west": {"uv": [48, 172], "uv_size": [1, 1]},
								"up": {"uv": [39, 170], "uv_size": [2, 1]},
								"down": {"uv": [42, 171], "uv_size": [2, -1]}
							}
						},
						{
							"origin": [4.75, 48.5, -4.25],
							"size": [3, 1, 10.25],
							"uv": {
								"north": {"uv": [166, 59], "uv_size": [3, 1]},
								"east": {"uv": [152, 15], "uv_size": [10.5, 1]},
								"south": {"uv": [166, 61], "uv_size": [3, 1]},
								"west": {"uv": [152, 17], "uv_size": [10.5, 1]},
								"up": {"uv": [106, 128], "uv_size": [3, 10.5]},
								"down": {"uv": [42, 146.5], "uv_size": [3, -10.5]}
							}
						},
						{
							"origin": [-7.75, 48.5, -4.25],
							"size": [3, 1, 10.25],
							"uv": {
								"north": {"uv": [169, 59], "uv_size": [-3, 1]},
								"east": {"uv": [162.5, 17], "uv_size": [-10.5, 1]},
								"south": {"uv": [169, 61], "uv_size": [-3, 1]},
								"west": {"uv": [162.5, 15], "uv_size": [-10.5, 1]},
								"up": {"uv": [179, 69], "uv_size": [-3, 10.5]},
								"down": {"uv": [45, 146.5], "uv_size": [-3, -10.5]}
							}
						},
						{
							"origin": [-7.75, 47.5, 2],
							"size": [3, 1, 3.75],
							"uv": {
								"north": {"uv": [41, 166], "uv_size": [3, 1]},
								"east": {"uv": [163, 82], "uv_size": [4, 1]},
								"south": {"uv": [45, 166], "uv_size": [3, 1]},
								"west": {"uv": [163, 137], "uv_size": [4, 1]},
								"up": {"uv": [109, 64], "uv_size": [3, 4]},
								"down": {"uv": [117, 62], "uv_size": [3, -4]}
							}
						},
						{
							"origin": [4.75, 47.5, 2],
							"size": [3, 1, 4],
							"uv": {
								"north": {"uv": [166, 45], "uv_size": [3, 1]},
								"east": {"uv": [163, 139], "uv_size": [4, 1]},
								"south": {"uv": [166, 55], "uv_size": [3, 1]},
								"west": {"uv": [164, 6], "uv_size": [4, 1]},
								"up": {"uv": [64, 118], "uv_size": [3, 4]},
								"down": {"uv": [134, 155], "uv_size": [3, -4]}
							}
						}
					]
				},
				{
					"name": "bone18",
					"parent": "jacket",
					"pivot": [6.25, 49.5, -4.25],
					"rotation": [-17.5, 0, 0],
					"cubes": [
						{
							"origin": [4.75, 47.5, -4.25],
							"size": [3, 2, 1],
							"uv": {
								"north": {"uv": [172, 59], "uv_size": [3, 2]},
								"east": {"uv": [174, 31], "uv_size": [1, 2]},
								"south": {"uv": [166, 61], "uv_size": [3, 1]},
								"west": {"uv": [174, 28], "uv_size": [1, 2]},
								"up": {"uv": [172, 58], "uv_size": [3, 1]},
								"down": {"uv": [172, 63], "uv_size": [3, -1]}
							}
						},
						{
							"origin": [5.25, 47, -4.25],
							"size": [2, 0.5, 1],
							"uv": {
								"north": {"uv": [173, 63], "uv_size": [2, 0.5]},
								"east": {"uv": [152, 15], "uv_size": [10.5, 1]},
								"south": {"uv": [166, 61], "uv_size": [3, 1]},
								"west": {"uv": [176, 60], "uv_size": [1, 0.5]},
								"up": {"uv": [176, 61], "uv_size": [2, 1]},
								"down": {"uv": [176, 60], "uv_size": [2, -1]}
							}
						}
					]
				},
				{
					"name": "bone19",
					"parent": "jacket",
					"pivot": [-6.25, 49.5, -4.25],
					"rotation": [-17.5, 0, 0],
					"cubes": [
						{
							"origin": [-7.75, 47.5, -4.25],
							"size": [3, 2, 1],
							"uv": {
								"north": {"uv": [175, 59], "uv_size": [-3, 2]},
								"east": {"uv": [175, 28], "uv_size": [-1, 2]},
								"south": {"uv": [169, 61], "uv_size": [-3, 1]},
								"west": {"uv": [175, 31], "uv_size": [-1, 2]},
								"up": {"uv": [175, 58], "uv_size": [-3, 1]},
								"down": {"uv": [175, 63], "uv_size": [-3, -1]}
							}
						},
						{
							"origin": [-7.25, 47, -4.25],
							"size": [2, 0.5, 1],
							"uv": {
								"north": {"uv": [175, 63], "uv_size": [-2, 0.5]},
								"east": {"uv": [177, 60], "uv_size": [-1, 0.5]},
								"south": {"uv": [169, 61], "uv_size": [-3, 1]},
								"west": {"uv": [162.5, 15], "uv_size": [-10.5, 1]},
								"up": {"uv": [178, 61], "uv_size": [-2, 1]},
								"down": {"uv": [178, 60], "uv_size": [-2, -1]}
							}
						}
					]
				},
				{
					"name": "jacket2",
					"parent": "jacket",
					"pivot": [0, 49, -4.3],
					"rotation": [-15, 0, 0],
					"cubes": [
						{
							"origin": [-7.5, 41.5, -4.3],
							"size": [15, 7.5, 2],
							"uv": {
								"north": {"uv": [94, 33], "uv_size": [15.5, 7.5]},
								"east": {"uv": [108, 0], "uv_size": [2, 7.5]},
								"south": {"uv": [94, 42], "uv_size": [15, 7.5]},
								"west": {"uv": [120, 141], "uv_size": [2, 7.5]},
								"up": {"uv": [136.5, 12], "uv_size": [15.5, 2]},
								"down": {"uv": [138, 121], "uv_size": [15, -2]}
							}
						}
					]
				},
				{
					"name": "jacket3",
					"parent": "jacket2",
					"pivot": [0, 41.5, -4.3],
					"rotation": [48, 0, 0],
					"cubes": [
						{
							"origin": [-7.5, 37.9, -4.3],
							"size": [15, 3.6, 2],
							"uv": {
								"north": {"uv": [24, 128], "uv_size": [15.5, 3.5]},
								"east": {"uv": [158, 37], "uv_size": [2, 3.5]},
								"south": {"uv": [76, 128], "uv_size": [15, 3.5]},
								"west": {"uv": [158, 42], "uv_size": [2, 3.5]},
								"up": {"uv": [138, 122], "uv_size": [15, 2]},
								"down": {"uv": [138, 135], "uv_size": [15, -2]}
							}
						}
					]
				},
				{
					"name": "Chest2",
					"parent": "Chest",
					"pivot": [0, 48.75, -4.25],
					"rotation": [-15, 0, 0],
					"cubes": [
						{
							"origin": [-0.75, 46.5, -4.75],
							"size": [1.5, 2, 1],
							"uv": {
								"north": {"uv": [139, 165], "uv_size": [1.5, 2]},
								"east": {"uv": [169, 147], "uv_size": [1, 2]},
								"south": {"uv": [142, 165], "uv_size": [1.5, 2]},
								"west": {"uv": [169, 150], "uv_size": [1, 2]},
								"up": {"uv": [171, 33], "uv_size": [1.5, 1]},
								"down": {"uv": [171, 36], "uv_size": [1.5, -1]}
							}
						},
						{
							"origin": [0.75, 46.25, -4.55],
							"size": [2.5, 2.35, 1],
							"uv": {
								"north": {"uv": [65, 158], "uv_size": [2.5, 2.5]},
								"east": {"uv": [166, 163], "uv_size": [1, 2.5]},
								"south": {"uv": [158, 69], "uv_size": [2.5, 2.5]},
								"west": {"uv": [164, 166], "uv_size": [1, 2.5]},
								"up": {"uv": [167, 4], "uv_size": [2.5, 1]},
								"down": {"uv": [18, 168], "uv_size": [2.5, -1]}
							}
						},
						{
							"origin": [-3.25, 46.25, -4.55],
							"size": [2.5, 2.35, 1],
							"uv": {
								"north": {"uv": [137, 158], "uv_size": [2.5, 2.5]},
								"east": {"uv": [22, 167], "uv_size": [1, 2.5]},
								"south": {"uv": [158, 154], "uv_size": [2.5, 2.5]},
								"west": {"uv": [24, 167], "uv_size": [1, 2.5]},
								"up": {"uv": [167, 37], "uv_size": [2.5, 1]},
								"down": {"uv": [167, 40], "uv_size": [2.5, -1]}
							}
						}
					]
				},
				{
					"name": "bone3",
					"parent": "Chest2",
					"pivot": [-0.5, 47.6, -4.4],
					"rotation": [0, 0, 25],
					"cubes": [
						{
							"origin": [-1.25, 43.6, -4.45],
							"size": [1.5, 4, 1],
							"uv": {
								"north": {"uv": [13, 159], "uv_size": [1.5, 4]},
								"east": {"uv": [3, 163], "uv_size": [1, 4]},
								"south": {"uv": [16, 159], "uv_size": [1.5, 4]},
								"west": {"uv": [5, 163], "uv_size": [1, 4]},
								"up": {"uv": [171, 37], "uv_size": [1.5, 1]},
								"down": {"uv": [171, 40], "uv_size": [1.5, -1]}
							}
						}
					]
				},
				{
					"name": "bone7",
					"parent": "Chest2",
					"pivot": [0.5, 47.6, -4.4],
					"rotation": [0, 0, -25],
					"cubes": [
						{
							"origin": [-0.25, 43.6, -4.45],
							"size": [1.5, 4, 1],
							"uv": {
								"north": {"uv": [35, 159], "uv_size": [1.5, 4]},
								"east": {"uv": [7, 163], "uv_size": [1, 4]},
								"south": {"uv": [72, 159], "uv_size": [1.5, 4]},
								"west": {"uv": [9, 163], "uv_size": [1, 4]},
								"up": {"uv": [171, 41], "uv_size": [1.5, 1]},
								"down": {"uv": [171, 47], "uv_size": [1.5, -1]}
							}
						}
					]
				},
				{
					"name": "ChestLeft",
					"parent": "Chest2",
					"pivot": [3.9, 48.75, -4.25],
					"rotation": [0, -0.64686, -2.41492],
					"cubes": [
						{
							"origin": [-0.35, 41.75, -4.25],
							"size": [7.4, 7, 2],
							"uv": {
								"north": {"uv": [126, 0], "uv_size": [7.5, 7]},
								"east": {"uv": [112, 77], "uv_size": [2, 7]},
								"south": {"uv": [127, 40], "uv_size": [7.5, 7]},
								"west": {"uv": [34, 148], "uv_size": [2, 7]},
								"up": {"uv": [68, 97], "uv_size": [7.5, 2]},
								"down": {"uv": [15, 121], "uv_size": [7.5, -2]}
							}
						}
					]
				},
				{
					"name": "subborn1",
					"parent": "ChestLeft",
					"pivot": [3.9, 41.75, -4.25],
					"rotation": [50, 0, 0],
					"cubes": [
						{
							"origin": [-0.45, 37.75, -4.25],
							"size": [7.5, 4, 2],
							"uv": {
								"north": {"uv": [64, 138], "uv_size": [7.5, 4]},
								"east": {"uv": [154, 73], "uv_size": [2, 4]},
								"south": {"uv": [138, 104], "uv_size": [7.5, 4]},
								"west": {"uv": [154, 78], "uv_size": [2, 4]},
								"up": {"uv": [145, 53], "uv_size": [7.5, 2]},
								"down": {"uv": [147, 104], "uv_size": [7.5, -2]}
							}
						}
					]
				},
				{
					"name": "ChestRight",
					"parent": "Chest2",
					"pivot": [-3.9, 48.75, -4.25],
					"rotation": [0, 0.64686, 2.41492],
					"cubes": [
						{
							"origin": [-7.05, 41.75, -4.25],
							"size": [7.4, 7, 2],
							"uv": {
								"north": {"uv": [128, 8], "uv_size": [7.5, 7]},
								"east": {"uv": [37, 148], "uv_size": [2, 7]},
								"south": {"uv": [15, 128], "uv_size": [7.5, 7]},
								"west": {"uv": [40, 148], "uv_size": [2, 7]},
								"up": {"uv": [147, 105], "uv_size": [7.5, 2]},
								"down": {"uv": [147, 110], "uv_size": [7.5, -2]}
							}
						}
					]
				},
				{
					"name": "subborn2",
					"parent": "ChestRight",
					"pivot": [-3.9, 41.75, -4.25],
					"rotation": [50, 0, 0],
					"cubes": [
						{
							"origin": [-7.05, 37.75, -4.25],
							"size": [7.5, 4, 2],
							"uv": {
								"north": {"uv": [138, 109], "uv_size": [7.5, 4]},
								"east": {"uv": [154, 83], "uv_size": [2, 4]},
								"south": {"uv": [138, 114], "uv_size": [7.5, 4]},
								"west": {"uv": [154, 119], "uv_size": [2, 4]},
								"up": {"uv": [147, 111], "uv_size": [7.5, 2]},
								"down": {"uv": [147, 116], "uv_size": [7.5, -2]}
							}
						}
					]
				},
				{
					"name": "Head",
					"parent": "Chest",
					"pivot": [0, 48.75, 0],
					"cubes": [
						{
							"origin": [-6, 48.75, -6.25],
							"size": [12, 12, 12],
							"uv": {
								"north": {"uv": [32, 11], "uv_size": [12, 12]},
								"east": {"uv": [28, 35], "uv_size": [12, 12]},
								"south": {"uv": [0, 38], "uv_size": [12, 12]},
								"west": {"uv": [13, 38], "uv_size": [12, 12]},
								"up": {"uv": [41, 35], "uv_size": [12, 12]},
								"down": {"uv": [45, 23], "uv_size": [12, -12]}
							}
						}
					]
				},
				{
					"name": "armor_head",
					"parent": "Head",
					"pivot": [-5.25, 35.25, 4.75],
					"cubes": [
						{
							"origin": [-6.5, 48.75, -6.75],
							"size": [13, 13, 13],
							"uv": {
								"north": {"uv": [231, 217], "uv_size": [12, 12]},
								"east": {"uv": [227, 241], "uv_size": [12, 12]},
								"south": {"uv": [199, 244], "uv_size": [12, 12]},
								"west": {"uv": [212, 244], "uv_size": [12, 12]},
								"up": {"uv": [240, 241], "uv_size": [12, 12]},
								"down": {"uv": [244, 229], "uv_size": [12, -12]}
							}
						}
					]
				},
				{
					"name": "bone15",
					"parent": "Head",
					"pivot": [0, 35.75, -2.5],
					"cubes": [
						{
							"origin": [-6.25, 61.75, -6.5],
							"size": [12.5, 1, 12.5],
							"uv": {
								"north": {"uv": [76, 148], "uv_size": [12.5, 1]},
								"east": {"uv": [148, 88], "uv_size": [12.5, 1]},
								"south": {"uv": [148, 90], "uv_size": [12.5, 1]},
								"west": {"uv": [148, 92], "uv_size": [12.5, 1]},
								"up": {"uv": [0, 24], "uv_size": [12.5, 12.5]},
								"down": {"uv": [14, 36.5], "uv_size": [12.5, -12.5]}
							}
						}
					]
				},
				{
					"name": "bone16",
					"parent": "bone15",
					"pivot": [0, 34.75, -1.5]
				},
				{
					"name": "bone21",
					"parent": "bone16",
					"pivot": [0, 61.625, 6],
					"rotation": [10, 0, 0],
					"cubes": [
						{
							"origin": [-6.25, 57.75, 5.25],
							"size": [12.5, 4, 1.75],
							"uv": {
								"north": {"uv": [131, 21], "uv_size": [12.5, 4]},
								"east": {"uv": [105, 155], "uv_size": [2, 4]},
								"south": {"uv": [131, 26], "uv_size": [12.5, 4]},
								"west": {"uv": [129, 155], "uv_size": [2, 4]},
								"up": {"uv": [140, 73], "uv_size": [12.5, 2]},
								"down": {"uv": [140, 78], "uv_size": [12.5, -2]}
							}
						}
					]
				},
				{
					"name": "bone22",
					"parent": "bone21",
					"pivot": [0, 58.725, 7],
					"rotation": [-10, 0, 0],
					"cubes": [
						{
							"origin": [-6.25, 52.76481, 5.41931],
							"size": [12.5, 5, 1.75],
							"uv": {
								"north": {"uv": [121, 66], "uv_size": [12.5, 5]},
								"east": {"uv": [78, 70], "uv_size": [2, 5]},
								"south": {"uv": [15, 122], "uv_size": [12.5, 5]},
								"west": {"uv": [29, 122], "uv_size": [2, 5]},
								"up": {"uv": [140, 79], "uv_size": [12.5, 2]},
								"down": {"uv": [140, 84], "uv_size": [12.5, -2]}
							}
						}
					]
				},
				{
					"name": "bone23",
					"parent": "bone22",
					"pivot": [0, 53.75, 7],
					"rotation": [-5, 0, 0],
					"cubes": [
						{
							"origin": [-6.25, 47.78332, 5.50453],
							"size": [12.5, 5, 1.75],
							"uv": {
								"north": {"uv": [131, 48], "uv_size": [12.5, 4]},
								"east": {"uv": [155, 154], "uv_size": [2, 4]},
								"south": {"uv": [131, 53], "uv_size": [12.5, 4]},
								"west": {"uv": [32, 156], "uv_size": [2, 4]},
								"up": {"uv": [140, 85], "uv_size": [12.5, 2]},
								"down": {"uv": [76, 143], "uv_size": [12.5, -2]}
							}
						}
					]
				},
				{
					"name": "bone24",
					"parent": "bone23",
					"pivot": [0.03125, 48.25, 7],
					"rotation": [-5, 0, 0],
					"cubes": [
						{
							"origin": [4, 47.05347, 5.70708],
							"size": [2, 0.75, 1.5],
							"uv": {
								"north": {"uv": [169, 99], "uv_size": [2, 1]},
								"east": {"uv": [170, 144], "uv_size": [1.5, 1]},
								"south": {"uv": [169, 101], "uv_size": [2, 1]},
								"west": {"uv": [147, 170], "uv_size": [1.5, 1]},
								"up": {"uv": [165, 115], "uv_size": [2, 1.5]},
								"down": {"uv": [116, 166.5], "uv_size": [2, -1.5]}
							}
						},
						{
							"origin": [4.25, 46.30347, 5.70708],
							"size": [1.5, 0.75, 1.5],
							"uv": {
								"north": {"uv": [150, 170], "uv_size": [1.5, 1]},
								"east": {"uv": [153, 170], "uv_size": [1.5, 1]},
								"south": {"uv": [170, 157], "uv_size": [1.5, 1]},
								"west": {"uv": [170, 162], "uv_size": [1.5, 1]},
								"up": {"uv": [149, 167], "uv_size": [1.5, 1.5]},
								"down": {"uv": [152, 168.5], "uv_size": [1.5, -1.5]}
							}
						},
						{
							"origin": [-5.75, 46.30347, 5.70708],
							"size": [1.5, 0.75, 1.5],
							"uv": {
								"north": {"uv": [170, 164], "uv_size": [1.5, 1]},
								"east": {"uv": [171, 3], "uv_size": [1.5, 1]},
								"south": {"uv": [171, 12], "uv_size": [1.5, 1]},
								"west": {"uv": [171, 14], "uv_size": [1.5, 1]},
								"up": {"uv": [155, 167], "uv_size": [1.5, 1.5]},
								"down": {"uv": [167, 158.5], "uv_size": [1.5, -1.5]}
							}
						},
						{
							"origin": [-6, 47.05347, 5.70708],
							"size": [2, 0.75, 1.5],
							"uv": {
								"north": {"uv": [169, 103], "uv_size": [2, 1]},
								"east": {"uv": [171, 18], "uv_size": [1.5, 1]},
								"south": {"uv": [169, 128], "uv_size": [2, 1]},
								"west": {"uv": [171, 20], "uv_size": [1.5, 1]},
								"up": {"uv": [122, 165], "uv_size": [2, 1.5]},
								"down": {"uv": [125, 166.5], "uv_size": [2, -1.5]}
							}
						},
						{
							"origin": [-3.75, 47.05347, 5.70708],
							"size": [7.5, 0.75, 1.5],
							"uv": {
								"north": {"uv": [156, 8], "uv_size": [7.5, 1]},
								"east": {"uv": [22, 171], "uv_size": [1.5, 1]},
								"south": {"uv": [156, 10], "uv_size": [7.5, 1]},
								"west": {"uv": [171, 22], "uv_size": [1.5, 1]},
								"up": {"uv": [151, 142], "uv_size": [7.5, 1.5]},
								"down": {"uv": [151, 146.5], "uv_size": [7.5, -1.5]}
							}
						},
						{
							"origin": [-3.5, 46.05347, 5.70708],
							"size": [3.25, 1, 1.5],
							"uv": {
								"north": {"uv": [165, 10], "uv_size": [3.5, 1]},
								"east": {"uv": [171, 24], "uv_size": [1.5, 1]},
								"south": {"uv": [18, 165], "uv_size": [3.5, 1]},
								"west": {"uv": [25, 171], "uv_size": [1.5, 1]},
								"up": {"uv": [159, 148], "uv_size": [3.5, 1.5]},
								"down": {"uv": [152, 160.5], "uv_size": [3.5, -1.5]}
							}
						},
						{
							"origin": [0.25, 46.05347, 5.70708],
							"size": [3.25, 1, 1.5],
							"uv": {
								"north": {"uv": [23, 165], "uv_size": [3.5, 1]},
								"east": {"uv": [171, 26], "uv_size": [1.5, 1]},
								"south": {"uv": [165, 63], "uv_size": [3.5, 1]},
								"west": {"uv": [171, 31], "uv_size": [1.5, 1]},
								"up": {"uv": [0, 160], "uv_size": [3.5, 1.5]},
								"down": {"uv": [45, 161.5], "uv_size": [3.5, -1.5]}
							}
						}
					]
				},
				{
					"name": "bone4",
					"parent": "bone15",
					"pivot": [-5.52778, 62.72222, 0.19444],
					"rotation": [0, 0, 10],
					"cubes": [
						{
							"origin": [-6.99475, 57.7456, -6.75],
							"size": [2, 4.25, 3.5],
							"uv": {
								"north": {"uv": [153, 125], "uv_size": [2, 4.5]},
								"east": {"uv": [145, 47], "uv_size": [3.5, 4.5]},
								"south": {"uv": [0, 154], "uv_size": [2, 4.5]},
								"west": {"uv": [146, 142], "uv_size": [3.5, 4.5]},
								"up": {"uv": [40, 156], "uv_size": [2, 3.5]},
								"down": {"uv": [69, 159.5], "uv_size": [2, -3.5]}
							}
						},
						{
							"origin": [-6.74475, 57.7456, -6.5],
							"size": [1.75, 4, 12.5],
							"uv": {
								"north": {"uv": [146, 154], "uv_size": [2, 4]},
								"east": {"uv": [92, 128], "uv_size": [12.5, 4]},
								"south": {"uv": [149, 154], "uv_size": [2, 4]},
								"west": {"uv": [129, 88], "uv_size": [12.5, 4]},
								"up": {"uv": [126, 139], "uv_size": [2, 12.5]},
								"down": {"uv": [0, 152.5], "uv_size": [2, -12.5]}
							}
						}
					]
				},
				{
					"name": "bone5",
					"parent": "bone4",
					"pivot": [-6.77778, 59.72222, 0.19444],
					"rotation": [0, 0, -10],
					"cubes": [
						{
							"origin": [-7.08849, 52.26989, -6.5],
							"size": [1.75, 5.5, 12.5],
							"uv": {
								"north": {"uv": [120, 150], "uv_size": [2, 5.5]},
								"east": {"uv": [115, 91], "uv_size": [12.5, 5.5]},
								"south": {"uv": [138, 151], "uv_size": [2, 5.5]},
								"west": {"uv": [117, 51], "uv_size": [12.5, 5.5]},
								"up": {"uv": [73, 138], "uv_size": [2, 12.5]},
								"down": {"uv": [11, 151.5], "uv_size": [2, -12.5]}
							}
						},
						{
							"origin": [-7.33849, 52.26989, -6.75],
							"size": [2, 5.5, 3.5],
							"uv": {
								"north": {"uv": [14, 152], "uv_size": [2, 5.5]},
								"east": {"uv": [61, 143], "uv_size": [3.5, 5.5]},
								"south": {"uv": [17, 152], "uv_size": [2, 5.5]},
								"west": {"uv": [66, 143], "uv_size": [3.5, 5.5]},
								"up": {"uv": [123, 156], "uv_size": [2, 3.5]},
								"down": {"uv": [156, 127.5], "uv_size": [2, -3.5]}
							}
						}
					]
				},
				{
					"name": "bone6",
					"parent": "bone5",
					"pivot": [-7.08849, 52.26989, -2.5],
					"rotation": [0, 0, -17.5],
					"cubes": [
						{
							"origin": [-7.08849, 50.26989, -6.5],
							"size": [1.75, 2, 12.5],
							"uv": {
								"north": {"uv": [84, 162], "uv_size": [2, 2]},
								"east": {"uv": [138, 139], "uv_size": [12.5, 2]},
								"south": {"uv": [162, 87], "uv_size": [2, 2]},
								"west": {"uv": [140, 31], "uv_size": [12.5, 2]},
								"up": {"uv": [31, 139], "uv_size": [2, 12.5]},
								"down": {"uv": [123, 151.5], "uv_size": [2, -12.5]}
							}
						},
						{
							"origin": [-7.33849, 49.26989, -6.75],
							"size": [2, 3, 3.5],
							"uv": {
								"north": {"uv": [142, 162], "uv_size": [2, 2]},
								"east": {"uv": [132, 156], "uv_size": [3.5, 2]},
								"south": {"uv": [152, 162], "uv_size": [2, 2]},
								"west": {"uv": [157, 0], "uv_size": [3.5, 2]},
								"up": {"uv": [126, 156], "uv_size": [2, 3.5]},
								"down": {"uv": [157, 76.5], "uv_size": [2, -3.5]}
							}
						},
						{
							"origin": [-7.08849, 48.26989, -0.5],
							"size": [1.25, 1, 6.5],
							"uv": {
								"north": {"uv": [170, 63], "uv_size": [1.5, 1]},
								"east": {"uv": [156, 129], "uv_size": [6.5, 1]},
								"south": {"uv": [65, 170], "uv_size": [1.5, 1]},
								"west": {"uv": [157, 152], "uv_size": [6.5, 1]},
								"up": {"uv": [20, 153], "uv_size": [1.5, 6.5]},
								"down": {"uv": [23, 159.5], "uv_size": [1.5, -6.5]}
							}
						},
						{
							"origin": [-7.08849, 49.26989, -1.5],
							"size": [1.25, 1, 7.5],
							"uv": {
								"north": {"uv": [170, 63], "uv_size": [1.5, 1]},
								"east": {"uv": [156, 129], "uv_size": [6.5, 1]},
								"south": {"uv": [65, 170], "uv_size": [1.5, 1]},
								"west": {"uv": [157, 152], "uv_size": [6.5, 1]},
								"up": {"uv": [20, 153], "uv_size": [1.5, 6.5]},
								"down": {"uv": [23, 159.5], "uv_size": [1.5, -6.5]}
							}
						},
						{
							"origin": [-7.08849, 47.26989, 0.5],
							"size": [1.25, 1, 2.25],
							"uv": {
								"north": {"uv": [170, 67], "uv_size": [1.5, 1]},
								"east": {"uv": [166, 132], "uv_size": [2.5, 1]},
								"south": {"uv": [70, 170], "uv_size": [1.5, 1]},
								"west": {"uv": [166, 134], "uv_size": [2.5, 1]},
								"up": {"uv": [15, 164], "uv_size": [1.5, 2.5]},
								"down": {"uv": [34, 166.5], "uv_size": [1.5, -2.5]}
							}
						},
						{
							"origin": [-7.08849, 46.76989, 1],
							"size": [1.25, 0.5, 1.5],
							"uv": {
								"north": {"uv": [90, 172], "uv_size": [1.5, 0.5]},
								"east": {"uv": [93, 172], "uv_size": [1.5, 0.5]},
								"south": {"uv": [172, 94], "uv_size": [1.5, 0.5]},
								"west": {"uv": [96, 172], "uv_size": [1.5, 0.5]},
								"up": {"uv": [53, 167], "uv_size": [1.5, 1.5]},
								"down": {"uv": [91, 168.5], "uv_size": [1.5, -1.5]}
							}
						},
						{
							"origin": [-7.08849, 47.26989, 3.25],
							"size": [1.25, 1, 2.75],
							"uv": {
								"north": {"uv": [73, 170], "uv_size": [1.5, 1]},
								"east": {"uv": [64, 123], "uv_size": [3, 1]},
								"south": {"uv": [76, 170], "uv_size": [1.5, 1]},
								"west": {"uv": [143, 102], "uv_size": [3, 1]},
								"up": {"uv": [129, 160], "uv_size": [1.5, 3]},
								"down": {"uv": [31, 164], "uv_size": [1.5, -3]}
							}
						},
						{
							"origin": [-7.08849, 46.26989, 4],
							"size": [1.25, 1, 1.75],
							"uv": {
								"north": {"uv": [79, 170], "uv_size": [1.5, 1]},
								"east": {"uv": [168, 136], "uv_size": [2, 1]},
								"south": {"uv": [82, 170], "uv_size": [1.5, 1]},
								"west": {"uv": [168, 138], "uv_size": [2, 1]},
								"up": {"uv": [85, 165], "uv_size": [1.5, 2]},
								"down": {"uv": [165, 89], "uv_size": [1.5, -2]}
							}
						},
						{
							"origin": [-7.33849, 48.26989, -6.5],
							"size": [1.5, 1, 3.25],
							"uv": {
								"north": {"uv": [170, 84], "uv_size": [1.5, 1]},
								"east": {"uv": [161, 164], "uv_size": [3.5, 1]},
								"south": {"uv": [85, 170], "uv_size": [1.5, 1]},
								"west": {"uv": [165, 0], "uv_size": [3.5, 1]},
								"up": {"uv": [81, 159], "uv_size": [1.5, 3.5]},
								"down": {"uv": [132, 162.5], "uv_size": [1.5, -3.5]}
							}
						},
						{
							"origin": [-7.33849, 47.26989, -6],
							"size": [1.5, 1, 1.75],
							"uv": {
								"north": {"uv": [88, 170], "uv_size": [1.5, 1]},
								"east": {"uv": [139, 168], "uv_size": [2, 1]},
								"south": {"uv": [91, 170], "uv_size": [1.5, 1]},
								"west": {"uv": [168, 140], "uv_size": [2, 1]},
								"up": {"uv": [88, 165], "uv_size": [1.5, 2]},
								"down": {"uv": [165, 92], "uv_size": [1.5, -2]}
							}
						},
						{
							"origin": [-7.33849, 46.76989, -5.75],
							"size": [1.5, 0.5, 1],
							"uv": {
								"north": {"uv": [172, 96], "uv_size": [1.5, 0.5]},
								"east": {"uv": [138, 172], "uv_size": [1, 0.5]},
								"south": {"uv": [172, 98], "uv_size": [1.5, 0.5]},
								"west": {"uv": [143, 172], "uv_size": [1, 0.5]},
								"up": {"uv": [96, 170], "uv_size": [1.5, 1]},
								"down": {"uv": [104, 171], "uv_size": [1.5, -1]}
							}
						}
					]
				},
				{
					"name": "bone17",
					"parent": "bone5",
					"pivot": [-6.75, 54.75, -2.5],
					"rotation": [0, 0, -5]
				},
				{
					"name": "bone11",
					"parent": "bone15",
					"pivot": [5.52778, 62.72222, 0.19444],
					"rotation": [0, 0, -10],
					"cubes": [
						{
							"origin": [4.99475, 57.7456, -6.75],
							"size": [2, 4.25, 3.5],
							"uv": {
								"north": {"uv": [154, 0], "uv_size": [2, 4.5]},
								"east": {"uv": [21, 147], "uv_size": [3.5, 4.5]},
								"south": {"uv": [3, 154], "uv_size": [2, 4.5]},
								"west": {"uv": [26, 147], "uv_size": [3.5, 4.5]},
								"up": {"uv": [157, 78], "uv_size": [2, 3.5]},
								"down": {"uv": [157, 86.5], "uv_size": [2, -3.5]}
							}
						},
						{
							"origin": [4.99475, 57.7456, -6.5],
							"size": [1.75, 4, 12.5],
							"uv": {
								"north": {"uv": [152, 154], "uv_size": [2, 4]},
								"east": {"uv": [129, 93], "uv_size": [12.5, 4]},
								"south": {"uv": [102, 155], "uv_size": [2, 4]},
								"west": {"uv": [131, 16], "uv_size": [12.5, 4]},
								"up": {"uv": [3, 140], "uv_size": [2, 12.5]},
								"down": {"uv": [46, 152.5], "uv_size": [2, -12.5]}
							}
						}
					]
				},
				{
					"name": "bone9",
					"parent": "bone11",
					"pivot": [6.79475, 57.9956, 0.5],
					"cubes": [
						{
							"origin": [7.24475, 57.7456, -1.25],
							"size": [1, 2, 2],
							"uv": {
								"north": {"uv": [142, 168], "uv_size": [1, 2]},
								"east": {"uv": [162, 90], "uv_size": [2, 2]},
								"south": {"uv": [168, 142], "uv_size": [1, 2]},
								"west": {"uv": [108, 162], "uv_size": [2, 2]},
								"up": {"uv": [160, 168], "uv_size": [1, 2]},
								"down": {"uv": [162, 170], "uv_size": [1, -2]}
							}
						},
						{
							"origin": [5.99475, 56.9956, 0.5],
							"size": [1, 2.25, 2],
							"uv": {
								"north": {"uv": [145, 166], "uv_size": [1, 2.5]},
								"east": {"uv": [102, 160], "uv_size": [2, 2.5]},
								"south": {"uv": [147, 166], "uv_size": [1, 2.5]},
								"west": {"uv": [105, 160], "uv_size": [2, 2.5]},
								"up": {"uv": [18, 169], "uv_size": [1, 2]},
								"down": {"uv": [20, 171], "uv_size": [1, -2]}
							}
						},
						{
							"origin": [6.24475, 57.9956, -1],
							"size": [1, 1.5, 1.5],
							"uv": {
								"north": {"uv": [57, 170], "uv_size": [1, 1.5]},
								"east": {"uv": [110, 167], "uv_size": [1.5, 1.5]},
								"south": {"uv": [107, 170], "uv_size": [1, 1.5]},
								"west": {"uv": [167, 111], "uv_size": [1.5, 1.5]},
								"up": {"uv": [109, 170], "uv_size": [1, 1.5]},
								"down": {"uv": [111, 171.5], "uv_size": [1, -1.5]}
							}
						},
						{
							"origin": [5.99475, 56.9956, -3],
							"size": [1, 2.25, 2],
							"uv": {
								"north": {"uv": [132, 166], "uv_size": [1, 2.5]},
								"east": {"uv": [160, 77], "uv_size": [2, 2.5]},
								"south": {"uv": [166, 141], "uv_size": [1, 2.5]},
								"west": {"uv": [160, 81], "uv_size": [2, 2.5]},
								"up": {"uv": [168, 163], "uv_size": [1, 2]},
								"down": {"uv": [13, 171], "uv_size": [1, -2]}
							}
						},
						{
							"origin": [5.79475, 54.9956, -1.5],
							"size": [1, 3.75, 1],
							"pivot": [6.79475, 57.9956, -1],
							"rotation": [-14.94548, 1.29256, 4.83045],
							"uv": {
								"north": {"uv": [40, 141], "uv_size": [1, 4]},
								"east": {"uv": [102, 141], "uv_size": [1, 4]},
								"south": {"uv": [135, 159], "uv_size": [1, 4]},
								"west": {"uv": [59, 160], "uv_size": [1, 4]},
								"up": {"uv": [171, 86], "uv_size": [1, 1]},
								"down": {"uv": [171, 89], "uv_size": [1, -1]}
							}
						},
						{
							"origin": [5.79475, 54.9956, 0],
							"size": [1, 3.75, 1],
							"pivot": [6.79475, 57.9956, 0.5],
							"rotation": [14.94548, -1.29256, 4.83045],
							"uv": {
								"north": {"uv": [54, 162], "uv_size": [1, 4]},
								"east": {"uv": [111, 162], "uv_size": [1, 4]},
								"south": {"uv": [120, 162], "uv_size": [1, 4]},
								"west": {"uv": [137, 162], "uv_size": [1, 4]},
								"up": {"uv": [171, 90], "uv_size": [1, 1]},
								"down": {"uv": [171, 93], "uv_size": [1, -1]}
							}
						}
					]
				},
				{
					"name": "bone10",
					"parent": "bone9",
					"pivot": [8.24475, 57.7456, -0.25],
					"rotation": [0, 0, 10],
					"cubes": [
						{
							"origin": [7.24475, 51.7456, -1.25],
							"size": [1, 2, 2],
							"uv": {
								"north": {"uv": [169, 41], "uv_size": [1, 2]},
								"east": {"uv": [162, 115], "uv_size": [2, 2]},
								"south": {"uv": [59, 169], "uv_size": [1, 2]},
								"west": {"uv": [139, 162], "uv_size": [2, 2]},
								"up": {"uv": [169, 92], "uv_size": [1, 2]},
								"down": {"uv": [94, 171], "uv_size": [1, -2]}
							}
						},
						{
							"origin": [7.74475, 53.7456, -1],
							"size": [1, 4, 1.5],
							"uv": {
								"north": {"uv": [61, 163], "uv_size": [1, 4]},
								"east": {"uv": [75, 159], "uv_size": [1.5, 4]},
								"south": {"uv": [63, 163], "uv_size": [1, 4]},
								"west": {"uv": [78, 159], "uv_size": [1.5, 4]},
								"up": {"uv": [156, 170], "uv_size": [1, 1.5]},
								"down": {"uv": [164, 171.5], "uv_size": [1, -1.5]}
							}
						},
						{
							"origin": [7.74475, 57.7456, -0.75],
							"size": [1, 1, 1],
							"uv": {
								"north": {"uv": [78, 172], "uv_size": [1, 1]},
								"east": {"uv": [80, 172], "uv_size": [1, 1]},
								"south": {"uv": [82, 172], "uv_size": [1, 1]},
								"west": {"uv": [84, 172], "uv_size": [1, 1]},
								"up": {"uv": [86, 172], "uv_size": [1, 1]},
								"down": {"uv": [88, 173], "uv_size": [1, -1]}
							}
						},
						{
							"origin": [7.74475, 51.7456, -0.75],
							"size": [1, 2, 1],
							"uv": {
								"north": {"uv": [170, 28], "uv_size": [1, 2]},
								"east": {"uv": [30, 170], "uv_size": [1, 2]},
								"south": {"uv": [32, 170], "uv_size": [1, 2]},
								"west": {"uv": [34, 170], "uv_size": [1, 2]},
								"up": {"uv": [42, 172], "uv_size": [1, 1]},
								"down": {"uv": [44, 173], "uv_size": [1, -1]}
							}
						},
						{
							"origin": [7.24475, 53.7456, -1.5],
							"size": [1, 4, 2.5],
							"uv": {
								"north": {"uv": [13, 164], "uv_size": [1, 4]},
								"east": {"uv": [85, 152], "uv_size": [2.5, 4]},
								"south": {"uv": [164, 14], "uv_size": [1, 4]},
								"west": {"uv": [10, 153], "uv_size": [2.5, 4]},
								"up": {"uv": [26, 167], "uv_size": [1, 2.5]},
								"down": {"uv": [167, 43.5], "uv_size": [1, -2.5]}
							}
						}
					]
				},
				{
					"name": "bone8",
					"parent": "bone10",
					"pivot": [8.24475, 51.70393, -0.25],
					"rotation": [0, 0, 5],
					"cubes": [
						{
							"origin": [7.24475, 50.7456, -1],
							"size": [1, 1, 1.5],
							"uv": {
								"north": {"uv": [99, 171], "uv_size": [1, 1]},
								"east": {"uv": [170, 111], "uv_size": [1.5, 1]},
								"south": {"uv": [101, 171], "uv_size": [1, 1]},
								"west": {"uv": [170, 113], "uv_size": [1.5, 1]},
								"up": {"uv": [170, 115], "uv_size": [1, 1.5]},
								"down": {"uv": [170, 119.5], "uv_size": [1, -1.5]}
							}
						},
						{
							"origin": [7.24475, 49.9956, -0.75],
							"size": [1, 0.75, 1],
							"uv": {
								"north": {"uv": [171, 105], "uv_size": [1, 1]},
								"east": {"uv": [171, 107], "uv_size": [1, 1]},
								"south": {"uv": [171, 109], "uv_size": [1, 1]},
								"west": {"uv": [113, 171], "uv_size": [1, 1]},
								"up": {"uv": [115, 171], "uv_size": [1, 1]},
								"down": {"uv": [117, 172], "uv_size": [1, -1]}
							}
						},
						{
							"origin": [7.24475, 49.4956, -0.5],
							"size": [1, 0.5, 0.5],
							"uv": {
								"north": {"uv": [145, 172], "uv_size": [1, 0.5]},
								"east": {"uv": [172, 154], "uv_size": [0.5, 0.5]},
								"south": {"uv": [147, 172], "uv_size": [1, 0.5]},
								"west": {"uv": [158, 172], "uv_size": [0.5, 0.5]},
								"up": {"uv": [149, 172], "uv_size": [1, 0.5]},
								"down": {"uv": [151, 172.5], "uv_size": [1, -0.5]}
							}
						}
					]
				},
				{
					"name": "bone12",
					"parent": "bone11",
					"pivot": [6.77778, 59.72222, 0.19444],
					"rotation": [0, 0, 10],
					"cubes": [
						{
							"origin": [5.33849, 52.26989, -6.5],
							"size": [1.75, 5.5, 12.5],
							"uv": {
								"north": {"uv": [73, 152], "uv_size": [2, 5.5]},
								"east": {"uv": [118, 33], "uv_size": [12.5, 5.5]},
								"south": {"uv": [76, 152], "uv_size": [2, 5.5]},
								"west": {"uv": [118, 98], "uv_size": [12.5, 5.5]},
								"up": {"uv": [49, 140], "uv_size": [2, 12.5]},
								"down": {"uv": [52, 152.5], "uv_size": [2, -12.5]}
							}
						},
						{
							"origin": [5.33849, 52.26989, -6.75],
							"size": [2, 5.5, 3.5],
							"uv": {
								"north": {"uv": [79, 152], "uv_size": [2, 5.5]},
								"east": {"uv": [143, 88], "uv_size": [3.5, 5.5]},
								"south": {"uv": [82, 152], "uv_size": [2, 5.5]},
								"west": {"uv": [143, 95], "uv_size": [3.5, 5.5]},
								"up": {"uv": [85, 157], "uv_size": [2, 3.5]},
								"down": {"uv": [157, 122.5], "uv_size": [2, -3.5]}
							}
						}
					]
				},
				{
					"name": "bone13",
					"parent": "bone12",
					"pivot": [7.08849, 52.26989, -2.5],
					"rotation": [0, 0, 17.5],
					"cubes": [
						{
							"origin": [5.33849, 50.26989, -6.5],
							"size": [1.75, 2, 12.5],
							"uv": {
								"north": {"uv": [162, 154], "uv_size": [2, 2]},
								"east": {"uv": [140, 34], "uv_size": [12.5, 2]},
								"south": {"uv": [155, 162], "uv_size": [2, 2]},
								"west": {"uv": [140, 70], "uv_size": [12.5, 2]},
								"up": {"uv": [55, 140], "uv_size": [2, 12.5]},
								"down": {"uv": [58, 152.5], "uv_size": [2, -12.5]}
							}
						},
						{
							"origin": [5.33849, 49.26989, -6.75],
							"size": [2, 3, 3.5],
							"uv": {
								"north": {"uv": [158, 162], "uv_size": [2, 2]},
								"east": {"uv": [157, 3], "uv_size": [3.5, 2]},
								"south": {"uv": [0, 163], "uv_size": [2, 2]},
								"west": {"uv": [158, 31], "uv_size": [3.5, 2]},
								"up": {"uv": [120, 157], "uv_size": [2, 3.5]},
								"down": {"uv": [10, 161.5], "uv_size": [2, -3.5]}
							}
						},
						{
							"origin": [5.83849, 48.26989, -0.5],
							"size": [1.25, 1, 6.5],
							"uv": {
								"north": {"uv": [119, 170], "uv_size": [1.5, 1]},
								"east": {"uv": [45, 158], "uv_size": [6.5, 1]},
								"south": {"uv": [170, 121], "uv_size": [1.5, 1]},
								"west": {"uv": [53, 158], "uv_size": [6.5, 1]},
								"up": {"uv": [26, 153], "uv_size": [1.5, 6.5]},
								"down": {"uv": [29, 159.5], "uv_size": [1.5, -6.5]}
							}
						},
						{
							"origin": [5.83849, 49.26989, -1.5],
							"size": [1.25, 1, 7.5],
							"uv": {
								"north": {"uv": [119, 170], "uv_size": [1.5, 1]},
								"east": {"uv": [45, 158], "uv_size": [6.5, 1]},
								"south": {"uv": [170, 121], "uv_size": [1.5, 1]},
								"west": {"uv": [53, 158], "uv_size": [6.5, 1]},
								"up": {"uv": [26, 153], "uv_size": [1.5, 6.5]},
								"down": {"uv": [29, 159.5], "uv_size": [1.5, -6.5]}
							}
						},
						{
							"origin": [5.83849, 47.26989, 0.5],
							"size": [1.25, 1, 2.25],
							"uv": {
								"north": {"uv": [122, 170], "uv_size": [1.5, 1]},
								"east": {"uv": [166, 145], "uv_size": [2.5, 1]},
								"south": {"uv": [170, 123], "uv_size": [1.5, 1]},
								"west": {"uv": [160, 166], "uv_size": [2.5, 1]},
								"up": {"uv": [56, 164], "uv_size": [1.5, 2.5]},
								"down": {"uv": [164, 113.5], "uv_size": [1.5, -2.5]}
							}
						},
						{
							"origin": [5.83849, 46.76989, 1],
							"size": [1.25, 0.5, 1.5],
							"uv": {
								"north": {"uv": [172, 100], "uv_size": [1.5, 0.5]},
								"east": {"uv": [172, 102], "uv_size": [1.5, 0.5]},
								"south": {"uv": [103, 172], "uv_size": [1.5, 0.5]},
								"west": {"uv": [172, 115], "uv_size": [1.5, 0.5]},
								"up": {"uv": [119, 167], "uv_size": [1.5, 1.5]},
								"down": {"uv": [134, 168.5], "uv_size": [1.5, -1.5]}
							}
						},
						{
							"origin": [5.83849, 47.26989, 3.25],
							"size": [1.25, 1, 2.75],
							"uv": {
								"north": {"uv": [125, 170], "uv_size": [1.5, 1]},
								"east": {"uv": [91, 165], "uv_size": [3, 1]},
								"south": {"uv": [170, 125], "uv_size": [1.5, 1]},
								"west": {"uv": [165, 93], "uv_size": [3, 1]},
								"up": {"uv": [69, 161], "uv_size": [1.5, 3]},
								"down": {"uv": [88, 164], "uv_size": [1.5, -3]}
							}
						},
						{
							"origin": [5.83849, 46.26989, 4],
							"size": [1.25, 1, 1.75],
							"uv": {
								"north": {"uv": [170, 130], "uv_size": [1.5, 1]},
								"east": {"uv": [169, 6], "uv_size": [2, 1]},
								"south": {"uv": [132, 170], "uv_size": [1.5, 1]},
								"west": {"uv": [169, 57], "uv_size": [2, 1]},
								"up": {"uv": [165, 105], "uv_size": [1.5, 2]},
								"down": {"uv": [107, 167], "uv_size": [1.5, -2]}
							}
						},
						{
							"origin": [5.83849, 48.26989, -6.5],
							"size": [1.5, 1, 3.25],
							"uv": {
								"north": {"uv": [170, 132], "uv_size": [1.5, 1]},
								"east": {"uv": [165, 2], "uv_size": [3.5, 1]},
								"south": {"uv": [170, 134], "uv_size": [1.5, 1]},
								"west": {"uv": [165, 8], "uv_size": [3.5, 1]},
								"up": {"uv": [146, 159], "uv_size": [1.5, 3.5]},
								"down": {"uv": [149, 162.5], "uv_size": [1.5, -3.5]}
							}
						},
						{
							"origin": [5.83849, 47.26989, -6],
							"size": [1.5, 1, 1.75],
							"uv": {
								"north": {"uv": [135, 170], "uv_size": [1.5, 1]},
								"east": {"uv": [169, 95], "uv_size": [2, 1]},
								"south": {"uv": [138, 170], "uv_size": [1.5, 1]},
								"west": {"uv": [169, 97], "uv_size": [2, 1]},
								"up": {"uv": [165, 108], "uv_size": [1.5, 2]},
								"down": {"uv": [113, 167], "uv_size": [1.5, -2]}
							}
						},
						{
							"origin": [5.83849, 46.76989, -5.75],
							"size": [1.5, 0.5, 1],
							"uv": {
								"north": {"uv": [172, 117], "uv_size": [1.5, 0.5]},
								"east": {"uv": [172, 152], "uv_size": [1, 0.5]},
								"south": {"uv": [119, 172], "uv_size": [1.5, 0.5]},
								"west": {"uv": [153, 172], "uv_size": [1, 0.5]},
								"up": {"uv": [170, 142], "uv_size": [1.5, 1]},
								"down": {"uv": [144, 171], "uv_size": [1.5, -1]}
							}
						}
					]
				},
				{
					"name": "bone14",
					"parent": "bone12",
					"pivot": [6.75, 54.75, -2.5],
					"rotation": [0, 0, 5]
				},
				{
					"name": "bone",
					"parent": "bone15",
					"pivot": [-0.125, 61.775, -6.5],
					"rotation": [-10, 0, 0],
					"cubes": [
						{
							"origin": [-6.25, 57.75, -7.5],
							"size": [12.5, 4, 1.75],
							"uv": {
								"north": {"uv": [135, 66], "uv_size": [12.5, 3]},
								"east": {"uv": [96, 19], "uv_size": [2, 3]},
								"south": {"uv": [137, 8], "uv_size": [12.5, 3]},
								"west": {"uv": [158, 158], "uv_size": [2, 3]},
								"up": {"uv": [139, 125], "uv_size": [12.5, 2]},
								"down": {"uv": [139, 130], "uv_size": [12.5, -2]}
							}
						}
					]
				},
				{
					"name": "bone2",
					"parent": "bone",
					"pivot": [-0.58929, 58.26071, -7.5],
					"rotation": [10, 0, 0],
					"cubes": [
						{
							"origin": [-2.5, 56.75776, -7.58868],
							"size": [5, 1, 1.75],
							"uv": {
								"north": {"uv": [160, 29], "uv_size": [5, 1]},
								"east": {"uv": [107, 98], "uv_size": [2, 1]},
								"south": {"uv": [50, 160], "uv_size": [5, 1]},
								"west": {"uv": [140, 37], "uv_size": [2, 1]},
								"up": {"uv": [24, 106], "uv_size": [5, 2]},
								"down": {"uv": [122, 90], "uv_size": [5, -2]}
							}
						},
						{
							"origin": [-6.25, 55.00776, -7.58868],
							"size": [2, 1, 1.75],
							"uv": {
								"north": {"uv": [28, 168], "uv_size": [2, 1]},
								"east": {"uv": [31, 168], "uv_size": [2, 1]},
								"south": {"uv": [168, 31], "uv_size": [2, 1]},
								"west": {"uv": [168, 33], "uv_size": [2, 1]},
								"up": {"uv": [21, 136], "uv_size": [2, 2]},
								"down": {"uv": [61, 142], "uv_size": [2, -2]}
							}
						},
						{
							"origin": [-6.25, 54.00776, -7.58868],
							"size": [1.5, 1, 1.75],
							"uv": {
								"north": {"uv": [170, 44], "uv_size": [1.5, 1]},
								"east": {"uv": [168, 47], "uv_size": [2, 1]},
								"south": {"uv": [45, 170], "uv_size": [1.5, 1]},
								"west": {"uv": [49, 168], "uv_size": [2, 1]},
								"up": {"uv": [134, 164], "uv_size": [1.5, 2]},
								"down": {"uv": [31, 167], "uv_size": [1.5, -2]}
							}
						},
						{
							"origin": [-6.25, 56.00776, -7.58868],
							"size": [2.5, 1, 1.75],
							"uv": {
								"north": {"uv": [128, 166], "uv_size": [2.5, 1]},
								"east": {"uv": [43, 168], "uv_size": [2, 1]},
								"south": {"uv": [166, 130], "uv_size": [2.5, 1]},
								"west": {"uv": [46, 168], "uv_size": [2, 1]},
								"up": {"uv": [77, 87], "uv_size": [2.5, 2]},
								"down": {"uv": [127, 50], "uv_size": [2.5, -2]}
							}
						},
						{
							"origin": [-3.6, 56.25776, -7.58868],
							"size": [0.75, 0.75, 1.75],
							"uv": {
								"north": {"uv": [129, 139], "uv_size": [1, 1]},
								"east": {"uv": [65, 168], "uv_size": [2, 1]},
								"south": {"uv": [40, 146], "uv_size": [1, 1]},
								"west": {"uv": [168, 65], "uv_size": [2, 1]},
								"up": {"uv": [168, 67], "uv_size": [1, 2]},
								"down": {"uv": [68, 170], "uv_size": [1, -2]}
							}
						},
						{
							"origin": [-3.45, 55.50776, -7.58868],
							"size": [0.4, 0.75, 1.75],
							"uv": {
								"north": {"uv": [172, 127], "uv_size": [0.5, 1]},
								"east": {"uv": [168, 70], "uv_size": [2, 1]},
								"south": {"uv": [132, 172], "uv_size": [0.5, 1]},
								"west": {"uv": [168, 72], "uv_size": [2, 1]},
								"up": {"uv": [63, 171], "uv_size": [0.5, 2]},
								"down": {"uv": [68, 173], "uv_size": [0.5, -2]}
							}
						},
						{
							"origin": [-6.25, 57.00776, -7.58868],
							"size": [3.5, 0.75, 1.75],
							"uv": {
								"north": {"uv": [129, 164], "uv_size": [3.5, 0.75]},
								"east": {"uv": [37, 168], "uv_size": [2, 1]},
								"south": {"uv": [145, 164], "uv_size": [3.5, 1]},
								"west": {"uv": [40, 168], "uv_size": [2, 1]},
								"up": {"uv": [156, 105], "uv_size": [3.5, 2]},
								"down": {"uv": [156, 110], "uv_size": [3.5, -2]}
							}
						},
						{
							"origin": [2.75, 56.50776, -7.58868],
							"size": [3.5, 0.75, 1.75],
							"uv": {
								"north": {"uv": [164, 103], "uv_size": [3.5, 1]},
								"east": {"uv": [34, 168], "uv_size": [2, 1]},
								"south": {"uv": [164, 128], "uv_size": [3.5, 1]},
								"west": {"uv": [168, 35], "uv_size": [2, 1]},
								"up": {"uv": [35, 156], "uv_size": [3.5, 2]},
								"down": {"uv": [156, 104], "uv_size": [3.5, -2]}
							}
						},
						{
							"origin": [3, 55.50776, -7.58868],
							"size": [3.25, 1, 1.75],
							"uv": {
								"north": {"uv": [164, 147], "uv_size": [3.5, 1]},
								"east": {"uv": [168, 78], "uv_size": [2, 1]},
								"south": {"uv": [164, 149], "uv_size": [3.5, 1]},
								"west": {"uv": [168, 80], "uv_size": [2, 1]},
								"up": {"uv": [156, 111], "uv_size": [3.5, 2]},
								"down": {"uv": [156, 116], "uv_size": [3.5, -2]}
							}
						},
						{
							"origin": [4.25, 54.50776, -7.58868],
							"size": [2, 1, 1.75],
							"uv": {
								"north": {"uv": [81, 168], "uv_size": [2, 1]},
								"east": {"uv": [168, 82], "uv_size": [2, 1]},
								"south": {"uv": [84, 168], "uv_size": [2, 1]},
								"west": {"uv": [168, 86], "uv_size": [2, 1]},
								"up": {"uv": [162, 63], "uv_size": [2, 2]},
								"down": {"uv": [65, 164], "uv_size": [2, -2]}
							}
						},
						{
							"origin": [4.75, 53.50776, -7.58868],
							"size": [1.5, 1, 1.75],
							"uv": {
								"north": {"uv": [54, 170], "uv_size": [1.5, 1]},
								"east": {"uv": [168, 105], "uv_size": [2, 1]},
								"south": {"uv": [170, 55], "uv_size": [1.5, 1]},
								"west": {"uv": [107, 168], "uv_size": [2, 1]},
								"up": {"uv": [165, 65], "uv_size": [1.5, 2]},
								"down": {"uv": [68, 167], "uv_size": [1.5, -2]}
							}
						},
						{
							"origin": [3.5, 54.00776, -7.58868],
							"size": [0.4, 0.75, 1.75],
							"uv": {
								"north": {"uv": [134, 172], "uv_size": [0.5, 1]},
								"east": {"uv": [87, 168], "uv_size": [2, 1]},
								"south": {"uv": [136, 172], "uv_size": [0.5, 1]},
								"west": {"uv": [168, 88], "uv_size": [2, 1]},
								"up": {"uv": [171, 71], "uv_size": [0.5, 2]},
								"down": {"uv": [171, 80], "uv_size": [0.5, -2]}
							}
						},
						{
							"origin": [3.3, 54.75776, -7.58868],
							"size": [0.8, 0.75, 1.75],
							"uv": {
								"north": {"uv": [69, 154], "uv_size": [1, 1]},
								"east": {"uv": [168, 90], "uv_size": [2, 1]},
								"south": {"uv": [38, 159], "uv_size": [1, 1]},
								"west": {"uv": [97, 168], "uv_size": [2, 1]},
								"up": {"uv": [100, 168], "uv_size": [1, 2]},
								"down": {"uv": [102, 170], "uv_size": [1, -2]}
							}
						},
						{
							"origin": [2.5, 57.25776, -7.58868],
							"size": [3.75, 0.5, 1.75],
							"uv": {
								"north": {"uv": [168, 74], "uv_size": [4, 0.5]},
								"east": {"uv": [171, 65], "uv_size": [2, 0.5]},
								"south": {"uv": [168, 76], "uv_size": [4, 0.5]},
								"west": {"uv": [171, 69], "uv_size": [2, 0.5]},
								"up": {"uv": [154, 131], "uv_size": [4, 2]},
								"down": {"uv": [154, 136], "uv_size": [4, -2]}
							}
						},
						{
							"origin": [-2.25, 55.75776, -7.58868],
							"size": [4.5, 1, 1.75],
							"uv": {
								"north": {"uv": [161, 41], "uv_size": [4.5, 1]},
								"east": {"uv": [166, 167], "uv_size": [2, 1]},
								"south": {"uv": [161, 43], "uv_size": [4.5, 1]},
								"west": {"uv": [2, 168], "uv_size": [2, 1]},
								"up": {"uv": [153, 12], "uv_size": [4.5, 2]},
								"down": {"uv": [123, 155], "uv_size": [4.5, -2]}
							}
						}
					]
				},
				{
					"name": "bone30",
					"parent": "bone2",
					"pivot": [-6.25, 54, -7.55],
					"rotation": [10, 0, 0],
					"cubes": [
						{
							"origin": [-6.25, 53.00776, -7.58868],
							"size": [1.25, 1, 1.75],
							"uv": {
								"north": {"uv": [48, 170], "uv_size": [1.5, 1]},
								"east": {"uv": [168, 49], "uv_size": [2, 1]},
								"south": {"uv": [51, 170], "uv_size": [1.5, 1]},
								"west": {"uv": [168, 51], "uv_size": [2, 1]},
								"up": {"uv": [50, 165], "uv_size": [1.5, 2]},
								"down": {"uv": [65, 167], "uv_size": [1.5, -2]}
							}
						},
						{
							"origin": [-6, 48.52295, -7.76233],
							"size": [1, 1, 1.75],
							"uv": {
								"north": {"uv": [76, 112], "uv_size": [1, 1]},
								"east": {"uv": [168, 53], "uv_size": [2, 1]},
								"south": {"uv": [48, 130], "uv_size": [1, 1]},
								"west": {"uv": [56, 168], "uv_size": [2, 1]},
								"up": {"uv": [61, 168], "uv_size": [1, 2]},
								"down": {"uv": [63, 170], "uv_size": [1, -2]}
							}
						},
						{
							"origin": [-5.5, 47.52295, -7.76233],
							"size": [1, 1, 1.75],
							"uv": {
								"north": {"uv": [38, 172], "uv_size": [1, 1]},
								"east": {"uv": [170, 8], "uv_size": [2, 1]},
								"south": {"uv": [40, 172], "uv_size": [1, 1]},
								"west": {"uv": [170, 10], "uv_size": [2, 1]},
								"up": {"uv": [15, 170], "uv_size": [1, 2]},
								"down": {"uv": [28, 172], "uv_size": [1, -2]}
							}
						},
						{
							"origin": [-6.25, 49.50776, -7.58868],
							"size": [1, 3.5, 1.75],
							"uv": {
								"north": {"uv": [79, 166], "uv_size": [1, 2.5]},
								"east": {"uv": [56, 160], "uv_size": [2, 2.5]},
								"south": {"uv": [105, 166], "uv_size": [1, 2.5]},
								"west": {"uv": [160, 73], "uv_size": [2, 2.5]},
								"up": {"uv": [137, 167], "uv_size": [1, 2]},
								"down": {"uv": [11, 170], "uv_size": [1, -2]}
							}
						}
					]
				},
				{
					"name": "bone29",
					"parent": "bone2",
					"pivot": [5.75, 53.5, -7.6],
					"rotation": [10, 0, 0],
					"cubes": [
						{
							"origin": [5, 52.50776, -7.58868],
							"size": [1.25, 1, 1.75],
							"uv": {
								"north": {"uv": [170, 59], "uv_size": [1.5, 1]},
								"east": {"uv": [168, 107], "uv_size": [2, 1]},
								"south": {"uv": [170, 61], "uv_size": [1.5, 1]},
								"west": {"uv": [168, 109], "uv_size": [2, 1]},
								"up": {"uv": [165, 68], "uv_size": [1.5, 2]},
								"down": {"uv": [82, 167], "uv_size": [1.5, -2]}
							}
						},
						{
							"origin": [5.25, 49.75776, -7.58868],
							"size": [1, 2.75, 1.75],
							"uv": {
								"north": {"uv": [113, 168], "uv_size": [1, 2]},
								"east": {"uv": [162, 66], "uv_size": [2, 2]},
								"south": {"uv": [168, 114], "uv_size": [1, 2]},
								"west": {"uv": [162, 69], "uv_size": [2, 2]},
								"up": {"uv": [115, 168], "uv_size": [1, 2]},
								"down": {"uv": [117, 170], "uv_size": [1, -2]}
							}
						},
						{
							"origin": [5, 48.77295, -7.76233],
							"size": [1, 1, 1.75],
							"uv": {
								"north": {"uv": [108, 160], "uv_size": [1, 1]},
								"east": {"uv": [122, 168], "uv_size": [2, 1]},
								"south": {"uv": [171, 81], "uv_size": [1, 1]},
								"west": {"uv": [125, 168], "uv_size": [2, 1]},
								"up": {"uv": [128, 168], "uv_size": [1, 2]},
								"down": {"uv": [130, 170], "uv_size": [1, -2]}
							}
						}
					]
				},
				{
					"name": "bone25",
					"parent": "bone2",
					"pivot": [0, 55.75, -7.6],
					"rotation": [12.5, 0, 0],
					"cubes": [
						{
							"origin": [1.25, 54.75776, -7.58868],
							"size": [0.5, 1, 1.75],
							"uv": {
								"north": {"uv": [172, 119], "uv_size": [0.5, 1]},
								"east": {"uv": [5, 168], "uv_size": [2, 1]},
								"south": {"uv": [122, 172], "uv_size": [0.5, 1]},
								"west": {"uv": [8, 168], "uv_size": [2, 1]},
								"up": {"uv": [11, 171], "uv_size": [0.5, 2]},
								"down": {"uv": [171, 50], "uv_size": [0.5, -2]}
							}
						},
						{
							"origin": [-1, 55.00776, -7.58868],
							"size": [2, 0.75, 1.75],
							"uv": {
								"north": {"uv": [15, 168], "uv_size": [2, 1]},
								"east": {"uv": [168, 18], "uv_size": [2, 1]},
								"south": {"uv": [168, 20], "uv_size": [2, 1]},
								"west": {"uv": [168, 22], "uv_size": [2, 1]},
								"up": {"uv": [80, 23], "uv_size": [2, 2]},
								"down": {"uv": [128, 18], "uv_size": [2, -2]}
							}
						},
						{
							"origin": [-0.6, 54.25776, -7.58868],
							"size": [1.2, 0.75, 1.75],
							"uv": {
								"north": {"uv": [26, 46], "uv_size": [1.2, 0.75]},
								"east": {"uv": [168, 24], "uv_size": [2, 1]},
								"south": {"uv": [24, 85], "uv_size": [1, 1]},
								"west": {"uv": [168, 26], "uv_size": [2, 1]},
								"up": {"uv": [114, 138], "uv_size": [1, 2]},
								"down": {"uv": [32, 155], "uv_size": [1, -2]}
							}
						},
						{
							"origin": [-1.75, 54.75776, -7.58868],
							"size": [0.5, 1, 1.75],
							"uv": {
								"north": {"uv": [124, 172], "uv_size": [0.5, 1]},
								"east": {"uv": [168, 12], "uv_size": [2, 1]},
								"south": {"uv": [126, 172], "uv_size": [0.5, 1]},
								"west": {"uv": [168, 14], "uv_size": [2, 1]},
								"up": {"uv": [171, 51], "uv_size": [0.5, 2]},
								"down": {"uv": [61, 173], "uv_size": [0.5, -2]}
							}
						}
					]
				},
				{
					"name": "bone26",
					"parent": "bone2",
					"pivot": [-1.25, 54.25, -7.5],
					"rotation": [7.5, 0, 0]
				},
				{
					"name": "Faces",
					"parent": "Head",
					"pivot": [-3, 48.75, -2.25]
				},
				{
					"name": "Excited",
					"parent": "Faces",
					"pivot": [-3, 48.75, -2.25],
					"cubes": [
						{
							"origin": [-6, 48.75, -6.35],
							"size": [12, 12, 1],
							"uv": {
								"north": {"uv": [0, 64], "uv_size": [12, 12]},
								"east": {"uv": [116, 148], "uv_size": [1, 12]},
								"south": {"uv": [13, 64], "uv_size": [12, 12]},
								"west": {"uv": [118, 148], "uv_size": [1, 12]},
								"up": {"uv": [150, 19], "uv_size": [12, 1]},
								"down": {"uv": [150, 22], "uv_size": [12, -1]}
							}
						}
					]
				},
				{
					"name": "Eye_Closed",
					"parent": "Faces",
					"pivot": [-3, 49.75, -2.25],
					"cubes": [
						{
							"origin": [-6, 48.75, -6.35],
							"size": [12, 12, 1],
							"uv": {
								"north": {"uv": [39, 61], "uv_size": [12, 12]},
								"east": {"uv": [100, 148], "uv_size": [1, 12]},
								"south": {"uv": [52, 61], "uv_size": [12, 12]},
								"west": {"uv": [114, 148], "uv_size": [1, 12]},
								"up": {"uv": [149, 67], "uv_size": [12, 1]},
								"down": {"uv": [129, 150], "uv_size": [12, -1]}
							}
						}
					]
				},
				{
					"name": "Pat",
					"parent": "Faces",
					"pivot": [-3, 49.75, -2.25],
					"cubes": [
						{
							"origin": [-6, 48.75, -6.35],
							"size": [12, 12, 1],
							"uv": {
								"north": {"uv": [52, 48], "uv_size": [12, 12]},
								"east": {"uv": [92, 148], "uv_size": [1, 12]},
								"south": {"uv": [54, 24], "uv_size": [12, 12]},
								"west": {"uv": [94, 148], "uv_size": [1, 12]},
								"up": {"uv": [146, 148], "uv_size": [12, 1]},
								"down": {"uv": [149, 62], "uv_size": [12, -1]}
							}
						}
					]
				},
				{
					"name": "Heal",
					"parent": "Faces",
					"pivot": [-3, 49.75, -2.25],
					"cubes": [
						{
							"origin": [-6, 48.75, -6.35],
							"size": [12, 12, 1],
							"uv": {
								"north": {"uv": [58, 0], "uv_size": [12, 12]},
								"east": {"uv": [96, 148], "uv_size": [1, 12]},
								"south": {"uv": [26, 61], "uv_size": [12, 12]},
								"west": {"uv": [98, 148], "uv_size": [1, 12]},
								"up": {"uv": [149, 63], "uv_size": [12, 1]},
								"down": {"uv": [149, 66], "uv_size": [12, -1]}
							}
						}
					]
				},
				{
					"name": "Sleep",
					"parent": "Faces",
					"pivot": [-3, 49.75, -2.25],
					"cubes": [
						{
							"origin": [-6, 48.75, -6.35],
							"size": [12, 12, 1],
							"uv": {
								"north": {"uv": [173, 80], "uv_size": [12, 12]},
								"east": {"uv": [96, 148], "uv_size": [1, 12]},
								"south": {"uv": [26, 61], "uv_size": [12, 12]},
								"west": {"uv": [98, 148], "uv_size": [1, 12]},
								"up": {"uv": [149, 63], "uv_size": [12, 1]},
								"down": {"uv": [149, 66], "uv_size": [12, -1]}
							}
						}
					]
				},
				{
					"name": "Normal",
					"parent": "Faces",
					"pivot": [-3, 48.75, -2.25],
					"cubes": [
						{
							"origin": [-6, 48.75, -6.35],
							"size": [12, 12, 1],
							"uv": {
								"north": {"uv": [26, 48], "uv_size": [12, 12]},
								"east": {"uv": [71, 143], "uv_size": [1, 12]},
								"south": {"uv": [39, 48], "uv_size": [12, 12]},
								"west": {"uv": [108, 147], "uv_size": [1, 12]},
								"up": {"uv": [148, 94], "uv_size": [12, 1]},
								"down": {"uv": [148, 97], "uv_size": [12, -1]}
							}
						}
					]
				},
				{
					"name": "injured",
					"parent": "Faces",
					"pivot": [-3, 48.75, -2.25],
					"cubes": [
						{
							"origin": [-6, 48.75, -6.35],
							"size": [12, 12, 1],
							"uv": {
								"north": {"uv": [71, 0], "uv_size": [12, 12]},
								"east": {"uv": [6, 150], "uv_size": [1, 12]},
								"south": {"uv": [26, 74], "uv_size": [12, 12]},
								"west": {"uv": [8, 150], "uv_size": [1, 12]},
								"up": {"uv": [150, 49], "uv_size": [12, 1]},
								"down": {"uv": [150, 52], "uv_size": [12, -1]}
							}
						}
					]
				},
				{
					"name": "faint",
					"parent": "Faces",
					"pivot": [-3, 48.75, -2.25],
					"cubes": [
						{
							"origin": [-6, 48.75, -6.35],
							"size": [12, 12, 1],
							"uv": {
								"north": {"uv": [39, 74], "uv_size": [12, 12]},
								"east": {"uv": [61, 150], "uv_size": [1, 12]},
								"south": {"uv": [52, 74], "uv_size": [12, 12]},
								"west": {"uv": [63, 150], "uv_size": [1, 12]},
								"up": {"uv": [76, 150], "uv_size": [12, 1]},
								"down": {"uv": [146, 151], "uv_size": [12, -1]}
							}
						}
					]
				},
				{
					"name": "flushed",
					"parent": "Faces",
					"pivot": [-3, 48.75, -2.25],
					"cubes": [
						{
							"origin": [-6, 48.75, -6.35],
							"size": [12, 12, 1],
							"uv": {
								"north": {"uv": [0, 51], "uv_size": [12, 12]},
								"east": {"uv": [43, 148], "uv_size": [1, 12]},
								"south": {"uv": [13, 51], "uv_size": [12, 12]},
								"west": {"uv": [90, 148], "uv_size": [1, 12]},
								"up": {"uv": [148, 98], "uv_size": [12, 1]},
								"down": {"uv": [148, 101], "uv_size": [12, -1]}
							}
						}
					]
				},
				{
					"name": "angry1",
					"parent": "Faces",
					"pivot": [-3, 48.75, -2.25],
					"cubes": [
						{
							"origin": [-6, 48.75, -6.35],
							"size": [12, 12, 1],
							"uv": {
								"north": {"uv": [65, 37], "uv_size": [12, 12]},
								"east": {"uv": [110, 149], "uv_size": [1, 12]},
								"south": {"uv": [65, 50], "uv_size": [12, 12]},
								"west": {"uv": [112, 149], "uv_size": [1, 12]},
								"up": {"uv": [150, 23], "uv_size": [12, 1]},
								"down": {"uv": [150, 26], "uv_size": [12, -1]}
							}
						}
					]
				},
				{
					"name": "angry2",
					"parent": "Faces",
					"pivot": [-3, 48.75, -2.25],
					"cubes": [
						{
							"origin": [-5.5, 56.5, -8.2],
							"size": [4, 4, 1],
							"pivot": [-3.75, 58.75, -6.95],
							"rotation": [0, 0, 45],
							"uv": {
								"north": {"uv": [145, 19], "uv_size": [4, 4]},
								"east": {"uv": [126, 8], "uv_size": [1, 4]},
								"south": {"uv": [145, 24], "uv_size": [4, 4]},
								"west": {"uv": [40, 128], "uv_size": [1, 4]},
								"up": {"uv": [135, 70], "uv_size": [4, 1]},
								"down": {"uv": [161, 46], "uv_size": [4, -1]}
							}
						},
						{
							"origin": [-6, 48.75, -6.35],
							"size": [12, 12, 1],
							"uv": {
								"north": {"uv": [65, 63], "uv_size": [12, 12]},
								"east": {"uv": [142, 149], "uv_size": [1, 12]},
								"south": {"uv": [67, 13], "uv_size": [12, 12]},
								"west": {"uv": [144, 149], "uv_size": [1, 12]},
								"up": {"uv": [150, 27], "uv_size": [12, 1]},
								"down": {"uv": [150, 48], "uv_size": [12, -1]}
							}
						}
					]
				},
				{
					"name": "LeftArm",
					"parent": "Chest",
					"pivot": [7, 45.5, 0],
					"rotation": [0, 0, -5],
					"cubes": [
						{
							"origin": [7.31537, 36.74715, -2.75],
							"size": [4.5, 12, 5.5],
							"uv": {
								"north": {"uv": [64, 125], "uv_size": [4.5, 12]},
								"east": {"uv": [118, 105], "uv_size": [5.5, 12]},
								"south": {"uv": [70, 125], "uv_size": [4.5, 12]},
								"west": {"uv": [118, 118], "uv_size": [5.5, 12]},
								"up": {"uv": [104, 140], "uv_size": [4.5, 5.5]},
								"down": {"uv": [34, 146.5], "uv_size": [4.5, -5.5]}
							}
						}
					]
				},
				{
					"name": "armor_leftarm",
					"parent": "LeftArm",
					"pivot": [7.5, 34.2548, 2.5],
					"cubes": [
						{
							"origin": [7.31537, 27.74715, -2.75],
							"size": [4.5, 21, 5.5],
							"uv": {
								"north": {"uv": [196.5, 234.5], "uv_size": [4.5, 12]},
								"east": {"uv": [250.5, 214.5], "uv_size": [5.5, 12]},
								"south": {"uv": [202.5, 234.5], "uv_size": [4.5, 12]},
								"west": {"uv": [250.5, 227.5], "uv_size": [5.5, 12]},
								"up": {"uv": [236.5, 249.5], "uv_size": [4.5, 5.5]},
								"down": {"uv": [166.5, 256], "uv_size": [4.5, -5.5]}
							}
						}
					]
				},
				{
					"name": "cosmetic_leftarm",
					"parent": "LeftArm",
					"pivot": [-0.85894, 31.75476, -2.5],
					"cubes": [
						{
							"origin": [6.81537, 36.74715, -3.25],
							"size": [5.5, 12.25, 6.75],
							"uv": {
								"north": {"uv": [115, 77], "uv_size": [5.5, 12.5]},
								"east": {"uv": [78, 100], "uv_size": [7, 12.5]},
								"south": {"uv": [118, 19], "uv_size": [5.5, 12.5]},
								"west": {"uv": [86, 100], "uv_size": [7, 12.5]},
								"up": {"uv": [90, 133], "uv_size": [5.5, 7]},
								"down": {"uv": [97, 140], "uv_size": [5.5, -7]}
							}
						}
					]
				},
				{
					"name": "LeftHand",
					"parent": "LeftArm",
					"pivot": [12.33065, 36.74719, 3.5],
					"cubes": [
						{
							"origin": [7.31537, 23.74715, -2.75],
							"size": [4.5, 13, 5.5],
							"uv": {
								"north": {"uv": [104, 114], "uv_size": [4.5, 13]},
								"east": {"uv": [76, 114], "uv_size": [5.5, 13]},
								"south": {"uv": [42, 122], "uv_size": [4.5, 13]},
								"west": {"uv": [83, 114], "uv_size": [5.5, 13]},
								"up": {"uv": [90, 141], "uv_size": [4.5, 5.5]},
								"down": {"uv": [96, 146.5], "uv_size": [4.5, -5.5]}
							}
						}
					]
				},
				{
					"name": "cosmetic_lefthand",
					"parent": "LeftHand",
					"pivot": [-0.85894, 33.75476, -2.5],
					"cubes": [
						{
							"origin": [6.81537, 27.74715, -3.25],
							"size": [5.5, 9, 6.75],
							"uv": {
								"north": {"uv": [7, 129], "uv_size": [5.5, 9]},
								"east": {"uv": [58, 13], "uv_size": [7, 9]},
								"south": {"uv": [131, 105], "uv_size": [5.5, 9]},
								"west": {"uv": [16, 77], "uv_size": [7, 9]},
								"up": {"uv": [76, 133], "uv_size": [5.5, 7]},
								"down": {"uv": [83, 140], "uv_size": [5.5, -7]}
							}
						}
					]
				},
				{
					"name": "itemOffHand",
					"parent": "LeftHand",
					"pivot": [9.14106, 23.75476, 0]
				},
				{
					"name": "RightArm",
					"parent": "Chest",
					"pivot": [-7, 45.5, 0],
					"rotation": [0, 0, 5],
					"cubes": [
						{
							"origin": [-11.81537, 36.74715, -2.75],
							"size": [4.5, 12, 5.5],
							"uv": {
								"north": {"uv": [68.5, 125], "uv_size": [-4.5, 12]},
								"east": {"uv": [123.5, 118], "uv_size": [-5.5, 12]},
								"south": {"uv": [74.5, 125], "uv_size": [-4.5, 12]},
								"west": {"uv": [123.5, 105], "uv_size": [-5.5, 12]},
								"up": {"uv": [108.5, 140], "uv_size": [-4.5, 5.5]},
								"down": {"uv": [38.5, 146.5], "uv_size": [-4.5, -5.5]}
							}
						}
					]
				},
				{
					"name": "armor_rightarm",
					"parent": "RightArm",
					"pivot": [-8.5, 34.25476, 2.5],
					"cubes": [
						{
							"origin": [-11.81537, 27.74715, -2.75],
							"size": [4.5, 21, 5.5],
							"uv": {
								"north": {"uv": [201, 234.5], "uv_size": [-4.5, 12]},
								"east": {"uv": [256, 227.5], "uv_size": [-5.5, 12]},
								"south": {"uv": [207, 234.5], "uv_size": [-4.5, 12]},
								"west": {"uv": [256, 214.5], "uv_size": [-5.5, 12]},
								"up": {"uv": [241, 249.5], "uv_size": [-4.5, 5.5]},
								"down": {"uv": [171, 256], "uv_size": [-4.5, -5.5]}
							}
						}
					]
				},
				{
					"name": "cosmetic_rightarm",
					"parent": "RightArm",
					"pivot": [0.85894, 31.75476, -2.5],
					"cubes": [
						{
							"origin": [-12.31537, 36.74715, -3.25],
							"size": [5.5, 12.25, 6.75],
							"uv": {
								"north": {"uv": [120.5, 77], "uv_size": [-5.5, 12.5]},
								"east": {"uv": [93, 100], "uv_size": [-7, 12.5]},
								"south": {"uv": [123.5, 19], "uv_size": [-5.5, 12.5]},
								"west": {"uv": [85, 100], "uv_size": [-7, 12.5]},
								"up": {"uv": [95.5, 133], "uv_size": [-5.5, 7]},
								"down": {"uv": [102.5, 140], "uv_size": [-5.5, -7]}
							}
						}
					]
				},
				{
					"name": "RightHand",
					"parent": "RightArm",
					"pivot": [-12.33065, 36.74719, 3.5],
					"cubes": [
						{
							"origin": [-11.81537, 23.74715, -2.75],
							"size": [4.5, 13, 5.5],
							"uv": {
								"north": {"uv": [108.5, 114], "uv_size": [-4.5, 13]},
								"east": {"uv": [88.5, 114], "uv_size": [-5.5, 13]},
								"south": {"uv": [46.5, 122], "uv_size": [-4.5, 13]},
								"west": {"uv": [81.5, 114], "uv_size": [-5.5, 13]},
								"up": {"uv": [94.5, 141], "uv_size": [-4.5, 5.5]},
								"down": {"uv": [100.5, 146.5], "uv_size": [-4.5, -5.5]}
							}
						}
					]
				},
				{
					"name": "cosmetic_righthand",
					"parent": "RightHand",
					"pivot": [0.85894, 33.75476, -2.5],
					"cubes": [
						{
							"origin": [-12.31537, 27.74715, -3.25],
							"size": [5.5, 9, 6.75],
							"uv": {
								"north": {"uv": [12.5, 129], "uv_size": [-5.5, 9]},
								"east": {"uv": [23, 77], "uv_size": [-7, 9]},
								"south": {"uv": [136.5, 105], "uv_size": [-5.5, 9]},
								"west": {"uv": [65, 13], "uv_size": [-7, 9]},
								"up": {"uv": [81.5, 133], "uv_size": [-5.5, 7]},
								"down": {"uv": [88.5, 140], "uv_size": [-5.5, -7]}
							}
						}
					]
				},
				{
					"name": "itemMainHand",
					"parent": "RightHand",
					"pivot": [-9.14106, 23.75476, 0]
				},
				{
					"name": "armor_body",
					"parent": "Body",
					"pivot": [-5.5, 36, 4],
					"cubes": [
						{
							"origin": [-6.75, 24, -4],
							"size": [13.5, 24.75, 8],
							"uv": {
								"north": {"uv": [225.5, 240], "uv_size": [13.5, 8.5]},
								"east": {"uv": [193.5, 174], "uv_size": [8, 8.5]},
								"south": {"uv": [240.5, 240], "uv_size": [13.5, 8.5]},
								"west": {"uv": [197.5, 150], "uv_size": [8, 8.5]},
								"up": {"uv": [242.5, 201], "uv_size": [13.5, 8]},
								"down": {"uv": [242.5, 218], "uv_size": [13.5, -8]}
							}
						}
					]
				},
				{
					"name": "cosmetic_body",
					"parent": "Body",
					"pivot": [0, 32.75, -2.5],
					"cubes": [
						{
							"origin": [-7, 32.25, -4.25],
							"size": [14, 7, 8.5],
							"uv": {
								"north": {"uv": [97, 77], "uv_size": [14.5, 7]},
								"east": {"uv": [122, 72], "uv_size": [8.5, 7]},
								"south": {"uv": [0, 98], "uv_size": [14.5, 7]},
								"west": {"uv": [122, 80], "uv_size": [8.5, 7]},
								"up": {"uv": [62, 87], "uv_size": [14, 8.5]},
								"down": {"uv": [0, 96.5], "uv_size": [14, -8.5]}
							}
						},
						{
							"origin": [-7.5, 31.25, -4.5],
							"size": [15, 2, 9.25],
							"uv": {
								"north": {"uv": [138, 136], "uv_size": [15.5, 2]},
								"east": {"uv": [84, 10], "uv_size": [9.5, 2]},
								"south": {"uv": [139, 58], "uv_size": [15.5, 2]},
								"west": {"uv": [143, 44], "uv_size": [9.5, 2]},
								"up": {"uv": [66.5, 26], "uv_size": [15.5, 9.5]},
								"down": {"uv": [65, 85.5], "uv_size": [15, -9.5]}
							}
						}
					]
				},
				{
					"name": "waist",
					"parent": "Body",
					"pivot": [0, 30.72151, 3.64286],
					"cubes": [
						{
							"origin": [-6.75, 23.02013, -3.81055],
							"size": [13.5, 1, 8],
							"uv": {
								"north": {"uv": [145, 56], "uv_size": [13.5, 1]},
								"east": {"uv": [154, 35], "uv_size": [8, 1]},
								"south": {"uv": [147, 117], "uv_size": [13.5, 1]},
								"west": {"uv": [154, 53], "uv_size": [8, 1]},
								"up": {"uv": [96, 10], "uv_size": [13.5, 8]},
								"down": {"uv": [15, 105], "uv_size": [13.5, -8]}
							}
						},
						{
							"origin": [-7.25, 24.02013, -4.31055],
							"size": [14.5, 7, 9],
							"uv": {
								"north": {"uv": [52, 97], "uv_size": [14.5, 7]},
								"east": {"uv": [32, 120], "uv_size": [9, 7]},
								"south": {"uv": [97, 69], "uv_size": [14.5, 7]},
								"west": {"uv": [121, 58], "uv_size": [9, 7]},
								"up": {"uv": [81, 80], "uv_size": [14.5, 9]},
								"down": {"uv": [83, 32], "uv_size": [14.5, -9]}
							}
						},
						{
							"origin": [-7.5, 20.27013, -4.56055],
							"size": [15, 11, 9.5],
							"uv": {
								"north": {"uv": [0, 0], "uv_size": [14.5, 11]},
								"east": {"uv": [30, 97], "uv_size": [9.5, 11]},
								"south": {"uv": [0, 12], "uv_size": [14.5, 11]},
								"west": {"uv": [41, 97], "uv_size": [9.5, 11]},
								"up": {"uv": [0, 77], "uv_size": [15, 9.5]},
								"down": {"uv": [78, 46.5], "uv_size": [15, -9.5]}
							}
						}
					]
				},
				{
					"name": "cosmetic_waist",
					"parent": "waist",
					"pivot": [0, 32.75, -2.5],
					"cubes": [
						{
							"origin": [-7.75, 27, -4.75],
							"size": [15.5, 4.5, 9.75],
							"uv": {
								"north": {"uv": [110, 45], "uv_size": [15.5, 4.5]},
								"east": {"uv": [132, 98], "uv_size": [10, 4.5]},
								"south": {"uv": [111, 13], "uv_size": [15.5, 4.5]},
								"west": {"uv": [24, 133], "uv_size": [10, 4.5]},
								"up": {"uv": [28, 24], "uv_size": [15.5, 10]},
								"down": {"uv": [32, 10], "uv_size": [15.5, -10]}
							}
						}
					]
				},
				{
					"name": "skirt",
					"parent": "waist",
					"pivot": [0, 32.02013, -0.31055]
				},
				{
					"name": "RightLeg",
					"parent": "waist",
					"pivot": [-3.75, 23.02013, 0.18945],
					"cubes": [
						{
							"origin": [-7, 12.02013, -3.31055],
							"size": [6.5, 12, 7],
							"uv": {
								"north": {"uv": [48.5, 109], "uv_size": [-6.5, 12]},
								"east": {"uv": [67, 105], "uv_size": [-7, 12]},
								"south": {"uv": [115.5, 51], "uv_size": [-6.5, 12]},
								"west": {"uv": [59, 105], "uv_size": [-7, 12]},
								"up": {"uv": [137.5, 58], "uv_size": [-6.5, 7]},
								"down": {"uv": [129.5, 138], "uv_size": [-6.5, -7]}
							}
						}
					]
				},
				{
					"name": "armor_rightleg",
					"parent": "RightLeg",
					"pivot": [-5, 23.0201, 3.1895],
					"cubes": [
						{
							"origin": [-7, 12.02013, -3.31055],
							"size": [6.5, 19, 7],
							"uv": {
								"north": {"uv": [111, 0], "uv_size": [6.5, 12]},
								"east": {"uv": [16, 106], "uv_size": [7, 12]},
								"south": {"uv": [110, 111], "uv_size": [6.5, 12]},
								"west": {"uv": [107, 85], "uv_size": [7, 12]},
								"up": {"uv": [48, 132], "uv_size": [6.5, 7]},
								"down": {"uv": [56, 139], "uv_size": [6.5, -7]}
							}
						}
					]
				},
				{
					"name": "RightLowerLeg",
					"parent": "RightLeg",
					"pivot": [-3.75, 12.02013, -3.06055],
					"cubes": [
						{
							"origin": [-7, 0.52013, -3.31055],
							"size": [6.5, 11.5, 7],
							"uv": {
								"north": {"uv": [116.5, 32], "uv_size": [-6.5, 11.5]},
								"east": {"uv": [15, 106], "uv_size": [-7, 11.5]},
								"south": {"uv": [116.5, 98], "uv_size": [-6.5, 11.5]},
								"west": {"uv": [7, 106], "uv_size": [-7, 11.5]},
								"up": {"uv": [137.5, 125], "uv_size": [-6.5, 7]},
								"down": {"uv": [138.5, 38], "uv_size": [-6.5, -7]}
							}
						},
						{
							"origin": [-7, 0.02013, -3.31055],
							"size": [6.5, 0.5, 3.5],
							"uv": {
								"north": {"uv": [118.5, 174], "uv_size": [-6.5, 0.5]},
								"east": {"uv": [111.5, 175], "uv_size": [-3.5, 0.5]},
								"south": {"uv": [107.5, 174], "uv_size": [-6.5, 0.5]},
								"west": {"uv": [101.5, 175], "uv_size": [-3.5, 0.5]},
								"up": {"uv": [137.5, 125], "uv_size": [-6.5, 7]},
								"down": {"uv": [138.5, 34.5], "uv_size": [-6.5, -3.5]}
							}
						},
						{
							"origin": [-7, 0.02013, 1.68945],
							"size": [6.5, 0.5, 2],
							"uv": {
								"north": {"uv": [118.5, 173], "uv_size": [-6.5, 0.5]},
								"east": {"uv": [111, 173], "uv_size": [-2, 0.5]},
								"south": {"uv": [107.5, 173], "uv_size": [-6.5, 0.5]},
								"west": {"uv": [100, 173], "uv_size": [-2, 0.5]},
								"up": {"uv": [137.5, 125], "uv_size": [-6.5, 7]},
								"down": {"uv": [138.5, 33], "uv_size": [-6.5, -2]}
							}
						}
					]
				},
				{
					"name": "armor_rightleg2",
					"parent": "RightLowerLeg",
					"pivot": [-5, 11.5201, 3.1895],
					"cubes": [
						{
							"origin": [-7, 0.02013, -3.31055],
							"size": [6.5, 12, 7],
							"uv": {
								"north": {"uv": [202, 243], "uv_size": [6.5, 11.5]},
								"east": {"uv": [226.5, 154.5], "uv_size": [7, 11.5]},
								"south": {"uv": [230.5, 199.5], "uv_size": [6.5, 11.5]},
								"west": {"uv": [141.5, 244.5], "uv_size": [7, 11.5]},
								"up": {"uv": [249.5, 207.5], "uv_size": [6.5, 7]},
								"down": {"uv": [249.5, 222.5], "uv_size": [6.5, -7]}
							}
						}
					]
				},
				{
					"name": "armor_rightfoot",
					"parent": "RightLowerLeg",
					"pivot": [-5, 11.5201, 3.1895],
					"cubes": [
						{
							"origin": [-7, 0.02013, -3.31055],
							"size": [6.5, 12, 7],
							"uv": {
								"north": {"uv": [202, 243], "uv_size": [6.5, 11.5]},
								"east": {"uv": [226.5, 154.5], "uv_size": [7, 11.5]},
								"south": {"uv": [230.5, 199.5], "uv_size": [6.5, 11.5]},
								"west": {"uv": [141.5, 244.5], "uv_size": [7, 11.5]},
								"up": {"uv": [249.5, 207.5], "uv_size": [6.5, 7]},
								"down": {"uv": [249.5, 222.5], "uv_size": [6.5, -7]}
							}
						}
					]
				},
				{
					"name": "LeftLeg",
					"parent": "waist",
					"pivot": [3.75, 23.02013, 0.18945],
					"cubes": [
						{
							"origin": [0.5, 12.02013, -3.31055],
							"size": [6.5, 12, 7],
							"uv": {
								"north": {"uv": [117.5, 0], "uv_size": [-6.5, 12]},
								"east": {"uv": [114, 85], "uv_size": [-7, 12]},
								"south": {"uv": [116.5, 111], "uv_size": [-6.5, 12]},
								"west": {"uv": [23, 106], "uv_size": [-7, 12]},
								"up": {"uv": [54.5, 132], "uv_size": [-6.5, 7]},
								"down": {"uv": [62.5, 139], "uv_size": [-6.5, -7]}
							}
						}
					]
				},
				{
					"name": "armor_leftleg",
					"parent": "LeftLeg",
					"pivot": [-0.25, 23.02013, 3.18945],
					"cubes": [
						{
							"origin": [0.5, 12.02013, -3.31055],
							"size": [6.5, 19, 7],
							"uv": {
								"north": {"uv": [117.5, 0], "uv_size": [-6.5, 12]},
								"east": {"uv": [114, 85], "uv_size": [-7, 12]},
								"south": {"uv": [116.5, 111], "uv_size": [-6.5, 12]},
								"west": {"uv": [23, 106], "uv_size": [-7, 12]},
								"up": {"uv": [54.5, 132], "uv_size": [-6.5, 7]},
								"down": {"uv": [62.5, 139], "uv_size": [-6.5, -7]}
							}
						}
					]
				},
				{
					"name": "LeftLowerLeg",
					"parent": "LeftLeg",
					"pivot": [3.75, 12.02013, -3.06055],
					"cubes": [
						{
							"origin": [0.5, 0.52013, -3.31055],
							"size": [6.5, 11.5, 7],
							"uv": {
								"north": {"uv": [74.5, 112], "uv_size": [-6.5, 11.5]},
								"east": {"uv": [31, 109], "uv_size": [-7, 11.5]},
								"south": {"uv": [119.5, 64], "uv_size": [-6.5, 11.5]},
								"west": {"uv": [116, 19], "uv_size": [-7, 11.5]},
								"up": {"uv": [138.5, 72], "uv_size": [-6.5, 7]},
								"down": {"uv": [138.5, 87], "uv_size": [-6.5, -7]}
							}
						},
						{
							"origin": [0.5, 0.02013, -3.31055],
							"size": [6.5, 0.5, 3.5],
							"uv": {
								"north": {"uv": [112, 174], "uv_size": [6.5, 0.5]},
								"east": {"uv": [98, 175], "uv_size": [3.5, 0.5]},
								"south": {"uv": [101, 174], "uv_size": [6.5, 0.5]},
								"west": {"uv": [108, 175], "uv_size": [3.5, 0.5]},
								"up": {"uv": [131, 125], "uv_size": [6.5, 7]},
								"down": {"uv": [132, 34.5], "uv_size": [6.5, -3.5]}
							}
						},
						{
							"origin": [0.5, 0.02013, 1.68945],
							"size": [6.5, 0.5, 2],
							"uv": {
								"north": {"uv": [112, 173], "uv_size": [6.5, 0.5]},
								"east": {"uv": [98, 173], "uv_size": [2, 0.5]},
								"south": {"uv": [101, 173], "uv_size": [6.5, 0.5]},
								"west": {"uv": [109, 173], "uv_size": [2, 0.5]},
								"up": {"uv": [131, 125], "uv_size": [6.5, 7]},
								"down": {"uv": [132, 33], "uv_size": [6.5, -2]}
							}
						}
					]
				},
				{
					"name": "armor_leftleg2",
					"parent": "LeftLowerLeg",
					"pivot": [-0.25, 11.52013, 3.1895],
					"cubes": [
						{
							"origin": [0.5, 0.02013, -3.31055],
							"size": [6.5, 12, 7],
							"uv": {
								"north": {"uv": [208.5, 243], "uv_size": [-6.5, 11.5]},
								"east": {"uv": [148.5, 244.5], "uv_size": [-7, 11.5]},
								"south": {"uv": [237, 199.5], "uv_size": [-6.5, 11.5]},
								"west": {"uv": [233.5, 154.5], "uv_size": [-7, 11.5]},
								"up": {"uv": [256, 207.5], "uv_size": [-6.5, 7]},
								"down": {"uv": [256, 222.5], "uv_size": [-6.5, -7]}
							}
						}
					]
				},
				{
					"name": "armor_leftfoot",
					"parent": "LeftLowerLeg",
					"pivot": [-0.25, 11.52013, 3.1895],
					"cubes": [
						{
							"origin": [0.5, 0.02013, -3.31055],
							"size": [6.5, 12, 7],
							"uv": {
								"north": {"uv": [208.5, 243], "uv_size": [-6.5, 11.5]},
								"east": {"uv": [148.5, 244.5], "uv_size": [-7, 11.5]},
								"south": {"uv": [237, 199.5], "uv_size": [-6.5, 11.5]},
								"west": {"uv": [233.5, 154.5], "uv_size": [-7, 11.5]},
								"up": {"uv": [256, 207.5], "uv_size": [-6.5, 7]},
								"down": {"uv": [256, 222.5], "uv_size": [-6.5, -7]}
							}
						}
					]
				}
			]
		}
	]
}