{
  "disc_fridaynight": {
    "sounds": [
      {
        "name": "projectazure:disc/fridaynight",
        "stream": true
      }
    ]
  },
  "disc_brainpower": {
    "sounds": [
      {
        "name": "projectazure:disc/brainpower",
        "stream": true
      }
    ]
  },
  "disc_rickroll": {
    "sounds": [
      {
        "name": "projectazure:disc/rickroll",
        "stream": true
      }
    ]
  },
  "disc_enterthebeginning": {
    "sounds": [
      {
        "name": "projectazure:disc/enterthebeginning",
        "stream": true
      }
    ]
  },
  "bonk": {
    "sounds": [
      {
        "name": "projectazure:weapon/misc/bonk"
      }
    ]
  },
  "gun_fire_medium": {
    "sounds": [
      {
        "name": "projectazure:weapon/gun/gun_fire_medium"
      }
    ]
  },
  "plane_gun": {
    "sounds": [
      {
        "name": "projectazure:entity/aircraft/aircraft_machinegun_fire"
      }
    ]
  },
  "rifle_suppressed": {
    "sounds": [
      {
        "name": "projectazure:weapon/rifle/rifle_suppressed"
      }
    ]
  },
  "gun_click": {
    "sounds": [
      {
        "name": "projectazure:weapon/rifle/gun_click"
      }
    ]
  },
  "chimera_projectile_launch": {
    "sounds": [
      {
        "name": "projectazure:entity/akn/chimera/projectile_launch"
      }
    ]
  },
  "chimera_projectile_impact": {
    "sounds": [
      {
        "name": "projectazure:entity/akn/chimera/projectile_impact"
      }
    ]
  },
  "hammer_swing": {
    "sounds": [
      {
        "name": "projectazure:entity/akn/mudrock/hammer_swing"
      }
    ]
  },
  "hammer_hit": {
    "sounds": [
      {
        "name": "projectazure:entity/akn/mudrock/hammer_hit"
      }
    ]
  },
  "chimera_talk_normal": {
    "sounds": [
      {
        "name": "projectazure:entity/akn/chimera/voice/voice1"
      },
      {
        "name": "projectazure:entity/akn/chimera/voice/voice2"
      },
      {
        "name": "projectazure:entity/akn/chimera/voice/voice3"
      },
      {
        "name": "projectazure:entity/akn/chimera/voice/voice4"
      },
      {
        "name": "projectazure:entity/akn/chimera/voice/voice5"
      },
      {
        "name": "projectazure:entity/akn/chimera/voice/voice6"
      },
      {
        "name": "projectazure:entity/akn/chimera/voice/voice7"
      }
    ]
  },
  "chimera_talk_high_affection1": {
    "sounds": [
      {
        "name": "projectazure:entity/akn/chimera/voice/voice1"
      },
      {
        "name": "projectazure:entity/akn/chimera/voice/voice2"
      },
      {
        "name": "projectazure:entity/akn/chimera/voice/voice3"
      },
      {
        "name": "projectazure:entity/akn/chimera/voice/voice4"
      },
      {
        "name": "projectazure:entity/akn/chimera/voice/voice5"
      },
      {
        "name": "projectazure:entity/akn/chimera/voice/voice6"
      },
      {
        "name": "projectazure:entity/akn/chimera/voice/voice7"
      },
      {
        "name": "projectazure:entity/akn/chimera/voice/voice_aff1"
      }
    ]
  },
  "chimera_talk_high_affection2": {
    "sounds": [
      {
        "name": "projectazure:entity/akn/chimera/voice/voice1"
      },
      {
        "name": "projectazure:entity/akn/chimera/voice/voice2"
      },
      {
        "name": "projectazure:entity/akn/chimera/voice/voice3"
      },
      {
        "name": "projectazure:entity/akn/chimera/voice/voice4"
      },
      {
        "name": "projectazure:entity/akn/chimera/voice/voice5"
      },
      {
        "name": "projectazure:entity/akn/chimera/voice/voice6"
      },
      {
        "name": "projectazure:entity/akn/chimera/voice/voice7"
      },
      {
        "name": "projectazure:entity/akn/chimera/voice/voice_aff1"
      },
      {
        "name": "projectazure:entity/akn/chimera/voice/voice_aff2"
      }
    ]
  },
  "chimera_talk_high_affection3": {
    "sounds": [
      {
        "name": "projectazure:entity/akn/chimera/voice/voice1"
      },
      {
        "name": "projectazure:entity/akn/chimera/voice/voice2"
      },
      {
        "name": "projectazure:entity/akn/chimera/voice/voice3"
      },
      {
        "name": "projectazure:entity/akn/chimera/voice/voice4"
      },
      {
        "name": "projectazure:entity/akn/chimera/voice/voice5"
      },
      {
        "name": "projectazure:entity/akn/chimera/voice/voice6"
      },
      {
        "name": "projectazure:entity/akn/chimera/voice/voice7"
      },
      {
        "name": "projectazure:entity/akn/chimera/voice/voice_aff1"
      },
      {
        "name": "projectazure:entity/akn/chimera/voice/voice_aff2"
      },
      {
        "name": "projectazure:entity/akn/chimera/voice/voice_aff3"
      }
    ]
  },
  "chen_talk_normal": {
    "sounds": [
      {
        "name": "projectazure:entity/akn/chen/voice/voice1"
      },
      {
        "name": "projectazure:entity/akn/chen/voice/voice2"
      },
      {
        "name": "projectazure:entity/akn/chen/voice/voice3"
      },
      {
        "name": "projectazure:entity/akn/chen/voice/voice4"
      },
      {
        "name": "projectazure:entity/akn/chen/voice/voice5"
      },
      {
        "name": "projectazure:entity/akn/chen/voice/voice6"
      },
      {
        "name": "projectazure:entity/akn/chen/voice/voice7"
      }
    ,
      {
        "name": "projectazure:entity/akn/chen/voice/voice8"
      }
    ]
  },
  "chen_talk_high_affection1": {
    "sounds": [
      {
        "name": "projectazure:entity/akn/chen/voice/voice1"
      },
      {
        "name": "projectazure:entity/akn/chen/voice/voice2"
      },
      {
        "name": "projectazure:entity/akn/chen/voice/voice3"
      },
      {
        "name": "projectazure:entity/akn/chen/voice/voice4"
      },
      {
        "name": "projectazure:entity/akn/chen/voice/voice5"
      },
      {
        "name": "projectazure:entity/akn/chen/voice/voice6"
      },
      {
        "name": "projectazure:entity/akn/chen/voice/voice7"
      },
      {
        "name": "projectazure:entity/akn/chen/voice/voice8"
      },
      {
        "name": "projectazure:entity/akn/chen/voice/voice_aff1"
      }
    ]
  },
  "chen_talk_high_affection2": {
    "sounds": [
      {
        "name": "projectazure:entity/akn/chen/voice/voice1"
      },
      {
        "name": "projectazure:entity/akn/chen/voice/voice2"
      },
      {
        "name": "projectazure:entity/akn/chen/voice/voice3"
      },
      {
        "name": "projectazure:entity/akn/chen/voice/voice4"
      },
      {
        "name": "projectazure:entity/akn/chen/voice/voice5"
      },
      {
        "name": "projectazure:entity/akn/chen/voice/voice6"
      },
      {
        "name": "projectazure:entity/akn/chen/voice/voice7"
      },
      {
        "name": "projectazure:entity/akn/chen/voice/voice8"
      },
      {
        "name": "projectazure:entity/akn/chen/voice/voice_aff1"
      },
      {
        "name": "projectazure:entity/akn/chen/voice/voice_aff2"
      }
    ]
  },
  "chen_talk_high_affection3": {
    "sounds": [
      {
        "name": "projectazure:entity/akn/chen/voice/voice1"
      },
      {
        "name": "projectazure:entity/akn/chen/voice/voice2"
      },
      {
        "name": "projectazure:entity/akn/chen/voice/voice3"
      },
      {
        "name": "projectazure:entity/akn/chen/voice/voice4"
      },
      {
        "name": "projectazure:entity/akn/chen/voice/voice5"
      },
      {
        "name": "projectazure:entity/akn/chen/voice/voice6"
      },
      {
        "name": "projectazure:entity/akn/chen/voice/voice7"
      },
      {
        "name": "projectazure:entity/akn/chen/voice/voice8"
      },
      {
        "name": "projectazure:entity/akn/chen/voice/voice_aff1"
      },
      {
        "name": "projectazure:entity/akn/chen/voice/voice_aff2"
      },
      {
        "name": "projectazure:entity/akn/chen/voice/voice_aff3"
      }
    ]
  },
  "mudrock_talk_normal": {
    "sounds": [
      {
        "name": "projectazure:entity/akn/mudrock/voice/voice1"
      },
      {
        "name": "projectazure:entity/akn/mudrock/voice/voice2"
      },
      {
        "name": "projectazure:entity/akn/mudrock/voice/voice3"
      },
      {
        "name": "projectazure:entity/akn/mudrock/voice/voice4"
      },
      {
        "name": "projectazure:entity/akn/mudrock/voice/voice5"
      },
      {
        "name": "projectazure:entity/akn/mudrock/voice/voice6"
      },
      {
        "name": "projectazure:entity/akn/mudrock/voice/voice7"
      }
    ]
  },
  "mudrock_talk_high_affection1": {
    "sounds": [
      {
        "name": "projectazure:entity/akn/mudrock/voice/voice1"
      },
      {
        "name": "projectazure:entity/akn/mudrock/voice/voice2"
      },
      {
        "name": "projectazure:entity/akn/mudrock/voice/voice3"
      },
      {
        "name": "projectazure:entity/akn/mudrock/voice/voice4"
      },
      {
        "name": "projectazure:entity/akn/mudrock/voice/voice5"
      },
      {
        "name": "projectazure:entity/akn/mudrock/voice/voice6"
      },
      {
        "name": "projectazure:entity/akn/mudrock/voice/voice7"
      },
      {
        "name": "projectazure:entity/akn/mudrock/voice/voice_aff1"
      }
    ]
  },
  "mudrock_talk_high_affection2": {
    "sounds": [
      {
        "name": "projectazure:entity/akn/mudrock/voice/voice1"
      },
      {
        "name": "projectazure:entity/akn/mudrock/voice/voice2"
      },
      {
        "name": "projectazure:entity/akn/mudrock/voice/voice3"
      },
      {
        "name": "projectazure:entity/akn/mudrock/voice/voice4"
      },
      {
        "name": "projectazure:entity/akn/mudrock/voice/voice5"
      },
      {
        "name": "projectazure:entity/akn/mudrock/voice/voice6"
      },
      {
        "name": "projectazure:entity/akn/mudrock/voice/voice7"
      },
      {
        "name": "projectazure:entity/akn/mudrock/voice/voice_aff1"
      },
      {
        "name": "projectazure:entity/akn/mudrock/voice/voice_aff2"
      }
    ]
  },
  "mudrock_talk_high_affection3": {
    "sounds": [
      {
        "name": "projectazure:entity/akn/mudrock/voice/voice1"
      },
      {
        "name": "projectazure:entity/akn/mudrock/voice/voice2"
      },
      {
        "name": "projectazure:entity/akn/mudrock/voice/voice3"
      },
      {
        "name": "projectazure:entity/akn/mudrock/voice/voice4"
      },
      {
        "name": "projectazure:entity/akn/mudrock/voice/voice5"
      },
      {
        "name": "projectazure:entity/akn/mudrock/voice/voice6"
      },
      {
        "name": "projectazure:entity/akn/mudrock/voice/voice7"
      },
      {
        "name": "projectazure:entity/akn/mudrock/voice/voice_aff1"
      },
      {
        "name": "projectazure:entity/akn/mudrock/voice/voice_aff2"
      },
      {
        "name": "projectazure:entity/akn/mudrock/voice/voice_aff3"
      }
    ]
  },
  "rosmontis_talk_normal": {
    "sounds": [
      {
        "name": "projectazure:entity/akn/rosmontis/voice/voice1"
      },
      {
        "name": "projectazure:entity/akn/rosmontis/voice/voice2"
      },
      {
        "name": "projectazure:entity/akn/rosmontis/voice/voice3"
      },
      {
        "name": "projectazure:entity/akn/rosmontis/voice/voice4"
      },
      {
        "name": "projectazure:entity/akn/rosmontis/voice/voice5"
      },
      {
        "name": "projectazure:entity/akn/rosmontis/voice/voice6"
      }
    ]
  },
  "rosmontis_talk_high_affection1": {
    "sounds": [
      {
        "name": "projectazure:entity/akn/rosmontis/voice/voice1"
      },
      {
        "name": "projectazure:entity/akn/rosmontis/voice/voice2"
      },
      {
        "name": "projectazure:entity/akn/rosmontis/voice/voice3"
      },
      {
        "name": "projectazure:entity/akn/rosmontis/voice/voice4"
      },
      {
        "name": "projectazure:entity/akn/rosmontis/voice/voice5"
      },
      {
        "name": "projectazure:entity/akn/rosmontis/voice/voice6"
      },
      {
        "name": "projectazure:entity/akn/rosmontis/voice/voice_aff1"
      }
    ]
  },
  "rosmontis_talk_high_affection2": {
    "sounds": [
      {
        "name": "projectazure:entity/akn/rosmontis/voice/voice1"
      },
      {
        "name": "projectazure:entity/akn/rosmontis/voice/voice2"
      },
      {
        "name": "projectazure:entity/akn/rosmontis/voice/voice3"
      },
      {
        "name": "projectazure:entity/akn/rosmontis/voice/voice4"
      },
      {
        "name": "projectazure:entity/akn/rosmontis/voice/voice5"
      },
      {
        "name": "projectazure:entity/akn/rosmontis/voice/voice6"
      },
      {
        "name": "projectazure:entity/akn/rosmontis/voice/voice7"
      },
      {
        "name": "projectazure:entity/akn/mudrock/voice/voice_aff1"
      },
      {
        "name": "projectazure:entity/akn/mudrock/voice/voice_aff2"
      }
    ]
  },
  "rosmontis_talk_high_affection3": {
    "sounds": [
      {
        "name": "projectazure:entity/akn/rosmontis/voice/voice1"
      },
      {
        "name": "projectazure:entity/akn/rosmontis/voice/voice2"
      },
      {
        "name": "projectazure:entity/akn/rosmontis/voice/voice3"
      },
      {
        "name": "projectazure:entity/akn/rosmontis/voice/voice4"
      },
      {
        "name": "projectazure:entity/akn/rosmontis/voice/voice5"
      },
      {
        "name": "projectazure:entity/akn/rosmontis/voice/voice6"
      },
      {
        "name": "projectazure:entity/akn/rosmontis/voice/voice_aff1"
      },
      {
        "name": "projectazure:entity/akn/rosmontis/voice/voice_aff2"
      },
      {
        "name": "projectazure:entity/akn/rosmontis/voice/voice_aff3"
      }
    ]
  },
  "sheath_hit": {
    "sounds": [
      {
        "name": "projectazure:entity/akn/chen/hit"
      }
    ]
  },
  "chixiao_hit": {
    "sounds": [
      {
        "name": "projectazure:entity/akn/chen/hit_heavy"
      }
    ]
  }
}